{
  "fetched": "2026-07-23T10:28:59Z",
  "today": "2026-07-23",
  "games": [
    {
      "home": "ATL",
      "away": "SD",
      "gameTime": "2026-07-23T16:15:00Z",
      "status": "Preview",
      "homeSP": {
        "id": 519242,
        "name": "Chris Sale"
      },
      "awaySP": {
        "id": 656288,
        "name": "Griffin Canning"
      }
    },
    {
      "home": "CLE",
      "away": "MIN",
      "gameTime": "2026-07-23T17:10:00Z",
      "status": "Preview",
      "homeSP": {
        "id": 668909,
        "name": "Gavin Williams"
      },
      "awaySP": {
        "id": 671737,
        "name": "Taj Bradley"
      }
    },
    {
      "home": "TOR",
      "away": "TB",
      "gameTime": "2026-07-23T19:07:00Z",
      "status": "Preview",
      "homeSP": {
        "id": 669456,
        "name": "Shane Bieber"
      },
      "awaySP": {
        "id": 693855,
        "name": "Ian Seymour"
      }
    },
    {
      "home": "STL",
      "away": "AZ",
      "gameTime": "2026-07-23T21:15:00Z",
      "status": "Preview",
      "homeSP": {
        "id": 700241,
        "name": "Michael McGreevy"
      },
      "awaySP": {
        "id": 694297,
        "name": "Brandon Pfaadt"
      }
    },
    {
      "home": "DET",
      "away": "KC",
      "gameTime": "2026-07-23T22:40:00Z",
      "status": "Preview",
      "homeSP": {
        "id": 675512,
        "name": "Troy Melton"
      },
      "awaySP": {
        "id": 677976,
        "name": "Randy Dobnak"
      }
    }
  ],
  "schedule": {
    "ATL": [
      "2026-07-23",
      "2026-07-24",
      "2026-07-25",
      "2026-07-26",
      "2026-07-27",
      "2026-07-28",
      "2026-07-29",
      "2026-07-30"
    ],
    "SD": [
      "2026-07-23",
      "2026-07-24",
      "2026-07-25",
      "2026-07-26",
      "2026-07-28",
      "2026-07-29",
      "2026-07-30"
    ],
    "CLE": [
      "2026-07-23",
      "2026-07-24",
      "2026-07-25",
      "2026-07-26",
      "2026-07-27",
      "2026-07-28",
      "2026-07-29"
    ],
    "MIN": [
      "2026-07-23",
      "2026-07-24",
      "2026-07-25",
      "2026-07-26",
      "2026-07-28",
      "2026-07-29",
      "2026-07-30"
    ],
    "TOR": [
      "2026-07-23",
      "2026-07-24",
      "2026-07-25",
      "2026-07-26",
      "2026-07-27",
      "2026-07-28",
      "2026-07-29"
    ],
    "TB": [
      "2026-07-23",
      "2026-07-24",
      "2026-07-25",
      "2026-07-26",
      "2026-07-28",
      "2026-07-29",
      "2026-07-30"
    ],
    "STL": [
      "2026-07-23",
      "2026-07-24",
      "2026-07-25",
      "2026-07-26",
      "2026-07-27",
      "2026-07-28",
      "2026-07-29",
      "2026-07-30"
    ],
    "AZ": [
      "2026-07-23",
      "2026-07-24",
      "2026-07-25",
      "2026-07-26",
      "2026-07-27",
      "2026-07-28",
      "2026-07-29"
    ],
    "DET": [
      "2026-07-23",
      "2026-07-24",
      "2026-07-25",
      "2026-07-26",
      "2026-07-27",
      "2026-07-28",
      "2026-07-29"
    ],
    "KC": [
      "2026-07-23",
      "2026-07-24",
      "2026-07-25",
      "2026-07-26",
      "2026-07-28",
      "2026-07-29",
      "2026-07-30"
    ],
    "MIL": [
      "2026-07-24",
      "2026-07-25",
      "2026-07-26",
      "2026-07-27",
      "2026-07-28",
      "2026-07-29"
    ],
    "COL": [
      "2026-07-24",
      "2026-07-25",
      "2026-07-26",
      "2026-07-28",
      "2026-07-29"
    ],
    "PIT": [
      "2026-07-24",
      "2026-07-25",
      "2026-07-26",
      "2026-07-27",
      "2026-07-28",
      "2026-07-29",
      "2026-07-30"
    ],
    "CHC": [
      "2026-07-24",
      "2026-07-25",
      "2026-07-26",
      "2026-07-27",
      "2026-07-28",
      "2026-07-29",
      "2026-07-30"
    ],
    "WSH": [
      "2026-07-24",
      "2026-07-25",
      "2026-07-26",
      "2026-07-27",
      "2026-07-28",
      "2026-07-29",
      "2026-07-30"
    ],
    "PHI": [
      "2026-07-24",
      "2026-07-25",
      "2026-07-26",
      "2026-07-27",
      "2026-07-28",
      "2026-07-29"
    ],
    "NYY": [
      "2026-07-24",
      "2026-07-25",
      "2026-07-26",
      "2026-07-27",
      "2026-07-28",
      "2026-07-29",
      "2026-07-30"
    ],
    "BAL": [
      "2026-07-24",
      "2026-07-25",
      "2026-07-26",
      "2026-07-27",
      "2026-07-28",
      "2026-07-29"
    ],
    "NYM": [
      "2026-07-24",
      "2026-07-25",
      "2026-07-26",
      "2026-07-27",
      "2026-07-28",
      "2026-07-29",
      "2026-07-30"
    ],
    "LAD": [
      "2026-07-24",
      "2026-07-25",
      "2026-07-26",
      "2026-07-28",
      "2026-07-29",
      "2026-07-30"
    ],
    "MIA": [
      "2026-07-24",
      "2026-07-25",
      "2026-07-26",
      "2026-07-27",
      "2026-07-28",
      "2026-07-29",
      "2026-07-30"
    ],
    "BOS": [
      "2026-07-24",
      "2026-07-25",
      "2026-07-26",
      "2026-07-27",
      "2026-07-28",
      "2026-07-29",
      "2026-07-30"
    ],
    "CWS": [
      "2026-07-24",
      "2026-07-25",
      "2026-07-26",
      "2026-07-27",
      "2026-07-28",
      "2026-07-29",
      "2026-07-30"
    ],
    "HOU": [
      "2026-07-24",
      "2026-07-25",
      "2026-07-26",
      "2026-07-27",
      "2026-07-28",
      "2026-07-29"
    ],
    "TEX": [
      "2026-07-24",
      "2026-07-25",
      "2026-07-26",
      "2026-07-27",
      "2026-07-28",
      "2026-07-29",
      "2026-07-30"
    ],
    "SEA": [
      "2026-07-24",
      "2026-07-25",
      "2026-07-26",
      "2026-07-27",
      "2026-07-28",
      "2026-07-29",
      "2026-07-30"
    ],
    "ATH": [
      "2026-07-24",
      "2026-07-25",
      "2026-07-26",
      "2026-07-27",
      "2026-07-28",
      "2026-07-29",
      "2026-07-30"
    ],
    "CIN": [
      "2026-07-24",
      "2026-07-25",
      "2026-07-26",
      "2026-07-27",
      "2026-07-28",
      "2026-07-29",
      "2026-07-30"
    ],
    "SF": [
      "2026-07-24",
      "2026-07-25",
      "2026-07-26",
      "2026-07-27",
      "2026-07-28",
      "2026-07-29",
      "2026-07-30"
    ],
    "LAA": [
      "2026-07-24",
      "2026-07-25",
      "2026-07-26",
      "2026-07-27",
      "2026-07-28",
      "2026-07-29"
    ]
  }
}