{
  "players": {
    "johnathan rodriguez": {
      "SLG": 0.0,
      "xSLG": 0.0,
      "Barrel%": null,
      "HardHit%": null,
      "EV50": null,
      "BABIP": 0.0,
      "xwOBA": null,
      "wOBA": 0.711
    },
    "chase delauter": {
      "SLG": 0.618,
      "xSLG": 0.599,
      "Barrel%": 17.8,
      "HardHit%": 51.1,
      "EV50": 96.082075111,
      "BABIP": 0.25,
      "xwOBA": null,
      "wOBA": 0.415
    },
    "will benson": {
      "SLG": 0.286,
      "xSLG": 0.194,
      "Barrel%": 0.0,
      "HardHit%": 22.2,
      "EV50": 92.862110625,
      "BABIP": 0.278,
      "xwOBA": null,
      "wOBA": 0.266
    },
    "tj rumfield": {
      "SLG": 0.464,
      "xSLG": 0.474,
      "Barrel%": 8.9,
      "HardHit%": 42.2,
      "EV50": 93.595180444,
      "BABIP": 0.349,
      "xwOBA": null,
      "wOBA": 0.369
    },
    "dalton rushing": {
      "SLG": 1.308,
      "xSLG": 1.098,
      "Barrel%": 30.0,
      "HardHit%": 60.0,
      "EV50": 100.549786667,
      "BABIP": 0.571,
      "xwOBA": null,
      "wOBA": 0.793
    },
    "bryce teodosio": {
      "SLG": 0.118,
      "xSLG": 0.184,
      "Barrel%": 9.1,
      "HardHit%": 18.2,
      "EV50": 91.094134,
      "BABIP": 0.2,
      "xwOBA": null,
      "wOBA": 0.141
    },
    "francisco alvarez": {
      "SLG": 0.565,
      "xSLG": 0.703,
      "Barrel%": 22.2,
      "HardHit%": 50.0,
      "EV50": 95.875321111,
      "BABIP": 0.281,
      "xwOBA": null,
      "wOBA": 0.416
    },
    "pj higgins": {
      "SLG": 0.167,
      "xSLG": 0.294,
      "Barrel%": 0.0,
      "HardHit%": 0.0,
      "EV50": 89.95116,
      "BABIP": 0.25,
      "xwOBA": null,
      "wOBA": 0.152
    },
    "samuel basallo": {
      "SLG": 0.362,
      "xSLG": 0.421,
      "Barrel%": 12.5,
      "HardHit%": 43.8,
      "EV50": 96.736019355,
      "BABIP": 0.172,
      "xwOBA": null,
      "wOBA": 0.286
    },
    "trevor larnach": {
      "SLG": 0.433,
      "xSLG": 0.5,
      "Barrel%": 12.5,
      "HardHit%": 45.8,
      "EV50": 93.786670833,
      "BABIP": 0.304,
      "xwOBA": null,
      "wOBA": 0.385
    },
    "ryan bliss": {
      "SLG": 0.0,
      "xSLG": 0.0,
      "Barrel%": null,
      "HardHit%": null,
      "EV50": null,
      "BABIP": 0.0,
      "xwOBA": null,
      "wOBA": 0.0
    },
    "tyrone taylor": {
      "SLG": 0.364,
      "xSLG": 0.408,
      "Barrel%": 5.0,
      "HardHit%": 20.0,
      "EV50": 91.927559,
      "BABIP": 0.158,
      "xwOBA": null,
      "wOBA": 0.258
    },
    "edgar quero": {
      "SLG": 0.146,
      "xSLG": 0.248,
      "Barrel%": 0.0,
      "HardHit%": 28.1,
      "EV50": 92.934384,
      "BABIP": 0.194,
      "xwOBA": null,
      "wOBA": 0.196
    },
    "ronny mauricio": {
      "SLG": 0.25,
      "xSLG": 0.301,
      "Barrel%": 0.0,
      "HardHit%": 50.0,
      "EV50": 97.54721,
      "BABIP": 0.5,
      "xwOBA": null,
      "wOBA": 0.227
    },
    "trea turner": {
      "SLG": 0.352,
      "xSLG": 0.287,
      "Barrel%": 1.8,
      "HardHit%": 27.3,
      "EV50": 92.393574,
      "BABIP": 0.315,
      "xwOBA": null,
      "wOBA": 0.293
    },
    "joc pederson": {
      "SLG": 0.316,
      "xSLG": 0.234,
      "Barrel%": 0.0,
      "HardHit%": 55.2,
      "EV50": 95.133552759,
      "BABIP": 0.25,
      "xwOBA": null,
      "wOBA": 0.272
    },
    "andy ibanez": {
      "SLG": 0.154,
      "xSLG": 0.251,
      "Barrel%": 0.0,
      "HardHit%": 27.3,
      "EV50": 92.370320909,
      "BABIP": 0.182,
      "xwOBA": null,
      "wOBA": 0.181
    },
    "kyle farmer": {
      "SLG": 0.5,
      "xSLG": 0.498,
      "Barrel%": 0.0,
      "HardHit%": 14.3,
      "EV50": 90.372511429,
      "BABIP": 0.286,
      "xwOBA": null,
      "wOBA": 0.315
    },
    "brice matthews": {
      "SLG": 0.292,
      "xSLG": 0.314,
      "Barrel%": 9.1,
      "HardHit%": 36.4,
      "EV50": 92.820454545,
      "BABIP": 0.2,
      "xwOBA": null,
      "wOBA": 0.239
    },
    "lane thomas": {
      "SLG": 0.192,
      "xSLG": 0.242,
      "Barrel%": 0.0,
      "HardHit%": 36.8,
      "EV50": 92.237265263,
      "BABIP": 0.211,
      "xwOBA": null,
      "wOBA": 0.259
    },
    "coby mayo": {
      "SLG": 0.184,
      "xSLG": 0.232,
      "Barrel%": 0.0,
      "HardHit%": 32.0,
      "EV50": 92.9434804,
      "BABIP": 0.24,
      "xwOBA": null,
      "wOBA": 0.23
    },
    "vinnie pasquantino": {
      "SLG": 0.159,
      "xSLG": 0.28,
      "Barrel%": 4.2,
      "HardHit%": 29.2,
      "EV50": 93.26144766,
      "BABIP": 0.188,
      "xwOBA": null,
      "wOBA": 0.196
    },
    "nick kurtz": {
      "SLG": 0.291,
      "xSLG": 0.389,
      "Barrel%": 14.3,
      "HardHit%": 60.7,
      "EV50": 99.430209643,
      "BABIP": 0.37,
      "xwOBA": null,
      "wOBA": 0.329
    },
    "spencer torkelson": {
      "SLG": 0.25,
      "xSLG": 0.418,
      "Barrel%": 9.7,
      "HardHit%": 48.4,
      "EV50": 94.794800645,
      "BABIP": 0.323,
      "xwOBA": null,
      "wOBA": 0.32
    },
    "alec burleson": {
      "SLG": 0.413,
      "xSLG": 0.593,
      "Barrel%": 12.1,
      "HardHit%": 51.7,
      "EV50": 95.763314035,
      "BABIP": 0.268,
      "xwOBA": null,
      "wOBA": 0.353
    },
    "steven kwan": {
      "SLG": 0.313,
      "xSLG": 0.318,
      "Barrel%": 1.7,
      "HardHit%": 6.7,
      "EV50": 89.759278772,
      "BABIP": 0.259,
      "xwOBA": null,
      "wOBA": 0.297
    },
    "jake meyers": {
      "SLG": 0.378,
      "xSLG": 0.456,
      "Barrel%": 13.3,
      "HardHit%": 33.3,
      "EV50": 92.554442,
      "BABIP": 0.276,
      "xwOBA": null,
      "wOBA": 0.32
    },
    "jose ramirez": {
      "SLG": 0.406,
      "xSLG": 0.529,
      "Barrel%": 11.9,
      "HardHit%": 40.7,
      "EV50": 94.529940339,
      "BABIP": 0.214,
      "xwOBA": null,
      "wOBA": 0.328
    },
    "luke raley": {
      "SLG": 0.556,
      "xSLG": 0.587,
      "Barrel%": 18.8,
      "HardHit%": 53.1,
      "EV50": 96.335900323,
      "BABIP": 0.448,
      "xwOBA": null,
      "wOBA": 0.401
    },
    "marcus semien": {
      "SLG": 0.266,
      "xSLG": 0.352,
      "Barrel%": 5.9,
      "HardHit%": 39.2,
      "EV50": 93.007055686,
      "BABIP": 0.22,
      "xwOBA": null,
      "wOBA": 0.235
    },
    "manny machado": {
      "SLG": 0.353,
      "xSLG": 0.392,
      "Barrel%": 7.3,
      "HardHit%": 34.1,
      "EV50": 93.199582683,
      "BABIP": 0.205,
      "xwOBA": null,
      "wOBA": 0.332
    },
    "luis torrens": {
      "SLG": 0.316,
      "xSLG": 0.425,
      "Barrel%": 0.0,
      "HardHit%": 52.9,
      "EV50": 94.578042353,
      "BABIP": 0.294,
      "xwOBA": null,
      "wOBA": 0.26
    },
    "brenton doyle": {
      "SLG": 0.271,
      "xSLG": 0.27,
      "Barrel%": 3.6,
      "HardHit%": 35.7,
      "EV50": 93.703431481,
      "BABIP": 0.296,
      "xwOBA": null,
      "wOBA": 0.252
    },
    "garrett mitchell": {
      "SLG": 0.436,
      "xSLG": 0.482,
      "Barrel%": 19.0,
      "HardHit%": 61.9,
      "EV50": 99.8679195,
      "BABIP": 0.526,
      "xwOBA": null,
      "wOBA": 0.391
    },
    "willy adames": {
      "SLG": 0.545,
      "xSLG": 0.459,
      "Barrel%": 12.0,
      "HardHit%": 40.0,
      "EV50": 93.543434,
      "BABIP": 0.319,
      "xwOBA": null,
      "wOBA": 0.38
    },
    "jared triolo": {
      "SLG": 0.261,
      "xSLG": 0.258,
      "Barrel%": 0.0,
      "HardHit%": 27.8,
      "EV50": 92.129474706,
      "BABIP": 0.278,
      "xwOBA": null,
      "wOBA": 0.273
    },
    "james wood": {
      "SLG": 0.574,
      "xSLG": 0.535,
      "Barrel%": 23.8,
      "HardHit%": 59.5,
      "EV50": 99.32044,
      "BABIP": 0.351,
      "xwOBA": null,
      "wOBA": 0.423
    },
    "pete alonso": {
      "SLG": 0.365,
      "xSLG": 0.392,
      "Barrel%": 7.0,
      "HardHit%": 58.1,
      "EV50": 97.079924419,
      "BABIP": 0.268,
      "xwOBA": null,
      "wOBA": 0.319
    },
    "maikel garcia": {
      "SLG": 0.455,
      "xSLG": 0.459,
      "Barrel%": 12.5,
      "HardHit%": 51.8,
      "EV50": 96.002852545,
      "BABIP": 0.315,
      "xwOBA": null,
      "wOBA": 0.364
    },
    "luke williams": {
      "SLG": 0.0,
      "xSLG": 0.0,
      "Barrel%": null,
      "HardHit%": null,
      "EV50": null,
      "BABIP": 0.0,
      "xwOBA": null,
      "wOBA": 0.711
    },
    "jake mangum": {
      "SLG": 0.257,
      "xSLG": 0.337,
      "Barrel%": 0.0,
      "HardHit%": 31.0,
      "EV50": 92.1030428,
      "BABIP": 0.286,
      "xwOBA": null,
      "wOBA": 0.258
    },
    "scott kingery": {
      "SLG": 0.0,
      "xSLG": 0.036,
      "Barrel%": 0.0,
      "HardHit%": 0.0,
      "EV50": 89.35741,
      "BABIP": 0.0,
      "xwOBA": null,
      "wOBA": 0.0
    },
    "cedric mullins": {
      "SLG": 0.255,
      "xSLG": 0.277,
      "Barrel%": 2.5,
      "HardHit%": 32.5,
      "EV50": 92.446466579,
      "BABIP": 0.158,
      "xwOBA": null,
      "wOBA": 0.197
    },
    "graham pauley": {
      "SLG": 0.3,
      "xSLG": 0.169,
      "Barrel%": 3.4,
      "HardHit%": 17.2,
      "EV50": 91.142442143,
      "BABIP": 0.25,
      "xwOBA": null,
      "wOBA": 0.22
    },
    "heliot ramos": {
      "SLG": 0.258,
      "xSLG": 0.266,
      "Barrel%": 5.1,
      "HardHit%": 38.5,
      "EV50": 94.793940789,
      "BABIP": 0.359,
      "xwOBA": null,
      "wOBA": 0.233
    },
    "nick yorke": {
      "SLG": 0.35,
      "xSLG": 0.391,
      "Barrel%": 6.3,
      "HardHit%": 50.0,
      "EV50": 95.693884063,
      "BABIP": 0.344,
      "xwOBA": null,
      "wOBA": 0.345
    },
    "cole young": {
      "SLG": 0.393,
      "xSLG": 0.355,
      "Barrel%": 7.0,
      "HardHit%": 27.9,
      "EV50": 92.108459535,
      "BABIP": 0.293,
      "xwOBA": null,
      "wOBA": 0.324
    },
    "gary sanchez": {
      "SLG": 0.815,
      "xSLG": 0.7,
      "Barrel%": 29.4,
      "HardHit%": 52.9,
      "EV50": 96.110540588,
      "BABIP": 0.167,
      "xwOBA": null,
      "wOBA": 0.51
    },
    "joey wiemer": {
      "SLG": 0.606,
      "xSLG": 0.411,
      "Barrel%": 10.0,
      "HardHit%": 40.0,
      "EV50": 94.865789474,
      "BABIP": 0.556,
      "xwOBA": null,
      "wOBA": 0.47
    },
    "tj friedl": {
      "SLG": 0.153,
      "xSLG": 0.154,
      "Barrel%": 0.0,
      "HardHit%": 17.1,
      "EV50": 91.311302353,
      "BABIP": 0.22,
      "xwOBA": null,
      "wOBA": 0.229
    },
    "matt wallner": {
      "SLG": 0.369,
      "xSLG": 0.347,
      "Barrel%": 8.8,
      "HardHit%": 50.0,
      "EV50": 96.005176765,
      "BABIP": 0.323,
      "xwOBA": null,
      "wOBA": 0.295
    },
    "daniel schneemann": {
      "SLG": 0.488,
      "xSLG": 0.5,
      "Barrel%": 10.3,
      "HardHit%": 51.7,
      "EV50": 95.419092414,
      "BABIP": 0.357,
      "xwOBA": null,
      "wOBA": 0.356
    },
    "sal stewart": {
      "SLG": 0.638,
      "xSLG": 0.629,
      "Barrel%": 21.3,
      "HardHit%": 51.1,
      "EV50": 96.680550435,
      "BABIP": 0.31,
      "xwOBA": null,
      "wOBA": 0.457
    },
    "brett sullivan": {
      "SLG": 0.4,
      "xSLG": 0.311,
      "Barrel%": 0.0,
      "HardHit%": 31.6,
      "EV50": 92.537810526,
      "BABIP": 0.368,
      "xwOBA": null,
      "wOBA": 0.317
    },
    "drew millas": {
      "SLG": 0.12,
      "xSLG": 0.224,
      "Barrel%": 0.0,
      "HardHit%": 5.3,
      "EV50": 88.533607778,
      "BABIP": 0.167,
      "xwOBA": null,
      "wOBA": 0.192
    },
    "george springer": {
      "SLG": 0.37,
      "xSLG": 0.351,
      "Barrel%": 10.0,
      "HardHit%": 42.5,
      "EV50": 93.81343225,
      "BABIP": 0.211,
      "xwOBA": null,
      "wOBA": 0.302
    },
    "miguel andujar": {
      "SLG": 0.432,
      "xSLG": 0.339,
      "Barrel%": 0.0,
      "HardHit%": 48.3,
      "EV50": 95.098104483,
      "BABIP": 0.379,
      "xwOBA": null,
      "wOBA": 0.351
    },
    "casey schmitt": {
      "SLG": 0.537,
      "xSLG": 0.429,
      "Barrel%": 10.7,
      "HardHit%": 53.6,
      "EV50": 96.148012143,
      "BABIP": 0.481,
      "xwOBA": null,
      "wOBA": 0.424
    },
    "jazz chisholm jr": {
      "SLG": 0.258,
      "xSLG": 0.211,
      "Barrel%": 4.8,
      "HardHit%": 33.3,
      "EV50": 93.233450244,
      "BABIP": 0.262,
      "xwOBA": null,
      "wOBA": 0.224
    },
    "jeff mcneil": {
      "SLG": 0.346,
      "xSLG": 0.356,
      "Barrel%": 0.0,
      "HardHit%": 33.3,
      "EV50": 92.35824881,
      "BABIP": 0.357,
      "xwOBA": null,
      "wOBA": 0.315
    },
    "taylor trammell": {
      "SLG": 0.385,
      "xSLG": 0.314,
      "Barrel%": 14.3,
      "HardHit%": 57.1,
      "EV50": 97.213938571,
      "BABIP": 0.571,
      "xwOBA": null,
      "wOBA": 0.363
    },
    "dominic smith": {
      "SLG": 0.684,
      "xSLG": 0.599,
      "Barrel%": 9.1,
      "HardHit%": 42.4,
      "EV50": 94.268735152,
      "BABIP": 0.4,
      "xwOBA": null,
      "wOBA": 0.474
    },
    "andy pages": {
      "SLG": 0.698,
      "xSLG": 0.49,
      "Barrel%": 8.9,
      "HardHit%": 55.6,
      "EV50": 95.780420889,
      "BABIP": 0.5,
      "xwOBA": null,
      "wOBA": 0.494
    },
    "nick loftin": {
      "SLG": 0.333,
      "xSLG": 0.353,
      "Barrel%": 12.5,
      "HardHit%": 37.5,
      "EV50": 93.9534325,
      "BABIP": 0.25,
      "xwOBA": null,
      "wOBA": 0.33
    },
    "tyler heineman": {
      "SLG": 0.333,
      "xSLG": 0.351,
      "Barrel%": 0.0,
      "HardHit%": 33.3,
      "EV50": 93.065175,
      "BABIP": 0.4,
      "xwOBA": null,
      "wOBA": 0.346
    },
    "jesus sanchez": {
      "SLG": 0.479,
      "xSLG": 0.508,
      "Barrel%": 7.9,
      "HardHit%": 44.7,
      "EV50": 94.617917895,
      "BABIP": 0.333,
      "xwOBA": null,
      "wOBA": 0.362
    },
    "jordan lawlar": {
      "SLG": 0.556,
      "xSLG": 0.474,
      "Barrel%": 8.3,
      "HardHit%": 41.7,
      "EV50": 95.877385833,
      "BABIP": 0.455,
      "xwOBA": null,
      "wOBA": 0.425
    },
    "nolan arenado": {
      "SLG": 0.31,
      "xSLG": 0.299,
      "Barrel%": 4.5,
      "HardHit%": 25.0,
      "EV50": 91.621313636,
      "BABIP": 0.214,
      "xwOBA": null,
      "wOBA": 0.225
    },
    "wilyer abreu": {
      "SLG": 0.561,
      "xSLG": 0.497,
      "Barrel%": 13.7,
      "HardHit%": 51.0,
      "EV50": 96.2121792,
      "BABIP": 0.396,
      "xwOBA": null,
      "wOBA": 0.415
    },
    "bryce johnson": {
      "SLG": 0.182,
      "xSLG": 0.087,
      "Barrel%": 0.0,
      "HardHit%": 16.7,
      "EV50": 90.303034,
      "BABIP": 0.2,
      "xwOBA": null,
      "wOBA": 0.167
    },
    "ryan mountcastle": {
      "SLG": 0.357,
      "xSLG": 0.348,
      "Barrel%": 0.0,
      "HardHit%": 41.7,
      "EV50": 95.526894167,
      "BABIP": 0.333,
      "xwOBA": null,
      "wOBA": 0.316
    },
    "edmundo sosa": {
      "SLG": 0.588,
      "xSLG": 0.54,
      "Barrel%": 6.7,
      "HardHit%": 40.0,
      "EV50": 94.419197333,
      "BABIP": 0.286,
      "xwOBA": null,
      "wOBA": 0.418
    },
    "nick gonzales": {
      "SLG": 0.306,
      "xSLG": 0.374,
      "Barrel%": 2.6,
      "HardHit%": 41.0,
      "EV50": 94.067025128,
      "BABIP": 0.308,
      "xwOBA": null,
      "wOBA": 0.281
    },
    "kyle higashioka": {
      "SLG": 0.476,
      "xSLG": 0.486,
      "Barrel%": 13.3,
      "HardHit%": 53.3,
      "EV50": 95.647386,
      "BABIP": 0.429,
      "xwOBA": null,
      "wOBA": 0.404
    },
    "everson pereira": {
      "SLG": 0.6,
      "xSLG": 0.636,
      "Barrel%": 27.3,
      "HardHit%": 54.5,
      "EV50": 97.026236364,
      "BABIP": 0.333,
      "xwOBA": null,
      "wOBA": 0.383
    },
    "tyler oneill": {
      "SLG": 0.345,
      "xSLG": 0.359,
      "Barrel%": 4.3,
      "HardHit%": 34.8,
      "EV50": 93.188306522,
      "BABIP": 0.273,
      "xwOBA": null,
      "wOBA": 0.329
    },
    "jake burger": {
      "SLG": 0.478,
      "xSLG": 0.463,
      "Barrel%": 12.8,
      "HardHit%": 53.2,
      "EV50": 96.232625957,
      "BABIP": 0.302,
      "xwOBA": null,
      "wOBA": 0.333
    },
    "ramon laureano": {
      "SLG": 0.567,
      "xSLG": 0.557,
      "Barrel%": 15.2,
      "HardHit%": 50.0,
      "EV50": 95.29771587,
      "BABIP": 0.31,
      "xwOBA": null,
      "wOBA": 0.401
    },
    "derek hill": {
      "SLG": 0.222,
      "xSLG": 0.285,
      "Barrel%": 0.0,
      "HardHit%": 40.0,
      "EV50": 93.10815,
      "BABIP": 0.4,
      "xwOBA": null,
      "wOBA": 0.295
    },
    "gleyber torres": {
      "SLG": 0.267,
      "xSLG": 0.353,
      "Barrel%": 6.4,
      "HardHit%": 23.4,
      "EV50": 91.152367021,
      "BABIP": 0.239,
      "xwOBA": null,
      "wOBA": 0.288
    },
    "jonah heim": {
      "SLG": 0.211,
      "xSLG": 0.206,
      "Barrel%": 6.3,
      "HardHit%": 18.8,
      "EV50": 90.388039375,
      "BABIP": 0.188,
      "xwOBA": null,
      "wOBA": 0.239
    },
    "joey ortiz": {
      "SLG": 0.2,
      "xSLG": 0.274,
      "Barrel%": 5.7,
      "HardHit%": 34.3,
      "EV50": 92.477259706,
      "BABIP": 0.265,
      "xwOBA": null,
      "wOBA": 0.205
    },
    "luis matos": {
      "SLG": 0.25,
      "xSLG": 0.183,
      "Barrel%": 0.0,
      "HardHit%": 50.0,
      "EV50": 96.015783333,
      "BABIP": 0.5,
      "xwOBA": null,
      "wOBA": 0.265
    },
    "blaze alexander": {
      "SLG": 0.237,
      "xSLG": 0.418,
      "Barrel%": 3.8,
      "HardHit%": 53.8,
      "EV50": 94.9294256,
      "BABIP": 0.32,
      "xwOBA": null,
      "wOBA": 0.24
    },
    "justin crawford": {
      "SLG": 0.404,
      "xSLG": 0.275,
      "Barrel%": 2.6,
      "HardHit%": 30.8,
      "EV50": 93.143772105,
      "BABIP": 0.385,
      "xwOBA": null,
      "wOBA": 0.342
    },
    "jose caballero": {
      "SLG": 0.286,
      "xSLG": 0.29,
      "Barrel%": 5.1,
      "HardHit%": 28.2,
      "EV50": 92.363419211,
      "BABIP": 0.237,
      "xwOBA": null,
      "wOBA": 0.231
    },
    "dominic canzone": {
      "SLG": 0.457,
      "xSLG": 0.558,
      "Barrel%": 13.8,
      "HardHit%": 48.3,
      "EV50": 96.13038931,
      "BABIP": 0.185,
      "xwOBA": null,
      "wOBA": 0.32
    },
    "carson williams": {
      "SLG": 0.174,
      "xSLG": 0.201,
      "Barrel%": 0.0,
      "HardHit%": 20.0,
      "EV50": 92.850607857,
      "BABIP": 0.214,
      "xwOBA": null,
      "wOBA": 0.159
    },
    "corbin carroll": {
      "SLG": 0.579,
      "xSLG": 0.55,
      "Barrel%": 12.2,
      "HardHit%": 43.9,
      "EV50": 94.967522683,
      "BABIP": 0.385,
      "xwOBA": null,
      "wOBA": 0.413
    },
    "matt chapman": {
      "SLG": 0.394,
      "xSLG": 0.333,
      "Barrel%": 3.8,
      "HardHit%": 34.0,
      "EV50": 94.664897308,
      "BABIP": 0.327,
      "xwOBA": null,
      "wOBA": 0.324
    },
    "ozzie albies": {
      "SLG": 0.435,
      "xSLG": 0.361,
      "Barrel%": 3.5,
      "HardHit%": 29.8,
      "EV50": 92.448879474,
      "BABIP": 0.315,
      "xwOBA": null,
      "wOBA": 0.348
    },
    "jose fernandez": {
      "SLG": 0.5,
      "xSLG": 0.419,
      "Barrel%": 9.4,
      "HardHit%": 34.4,
      "EV50": 94.226333548,
      "BABIP": 0.4,
      "xwOBA": null,
      "wOBA": 0.362
    },
    "andres chaparro": {
      "SLG": 0.5,
      "xSLG": 0.994,
      "Barrel%": 25.0,
      "HardHit%": 75.0,
      "EV50": 98.762505,
      "BABIP": 0.5,
      "xwOBA": null,
      "wOBA": 0.416
    },
    "javier sanoja": {
      "SLG": 0.429,
      "xSLG": 0.322,
      "Barrel%": 2.8,
      "HardHit%": 36.1,
      "EV50": 93.234641389,
      "BABIP": 0.417,
      "xwOBA": null,
      "wOBA": 0.361
    },
    "paul goldschmidt": {
      "SLG": 0.533,
      "xSLG": 0.378,
      "Barrel%": 10.0,
      "HardHit%": 40.0,
      "EV50": 94.646851,
      "BABIP": 0.222,
      "xwOBA": null,
      "wOBA": 0.399
    },
    "davis schneider": {
      "SLG": 0.458,
      "xSLG": 0.456,
      "Barrel%": 26.7,
      "HardHit%": 60.0,
      "EV50": 97.59247,
      "BABIP": 0.357,
      "xwOBA": null,
      "wOBA": 0.39
    },
    "luis arraez": {
      "SLG": 0.417,
      "xSLG": 0.353,
      "Barrel%": 0.0,
      "HardHit%": 18.6,
      "EV50": 90.896088276,
      "BABIP": 0.345,
      "xwOBA": null,
      "wOBA": 0.347
    },
    "spencer horwitz": {
      "SLG": 0.326,
      "xSLG": 0.225,
      "Barrel%": 0.0,
      "HardHit%": 26.5,
      "EV50": 91.510045882,
      "BABIP": 0.273,
      "xwOBA": null,
      "wOBA": 0.315
    },
    "rob refsnyder": {
      "SLG": 0.0,
      "xSLG": 0.102,
      "Barrel%": 0.0,
      "HardHit%": 27.3,
      "EV50": 91.478231818,
      "BABIP": 0.0,
      "xwOBA": null,
      "wOBA": 0.112
    },
    "bobby witt jr": {
      "SLG": 0.317,
      "xSLG": 0.461,
      "Barrel%": 11.8,
      "HardHit%": 54.9,
      "EV50": 97.341974118,
      "BABIP": 0.333,
      "xwOBA": null,
      "wOBA": 0.31
    },
    "jj wetherholt": {
      "SLG": 0.385,
      "xSLG": 0.388,
      "Barrel%": 7.7,
      "HardHit%": 40.4,
      "EV50": 93.712911569,
      "BABIP": 0.245,
      "xwOBA": null,
      "wOBA": 0.331
    },
    "mickey moniak": {
      "SLG": 0.649,
      "xSLG": 0.552,
      "Barrel%": 13.8,
      "HardHit%": 31.0,
      "EV50": 92.961037931,
      "BABIP": 0.167,
      "xwOBA": null,
      "wOBA": 0.382
    },
    "jorge mateo": {
      "SLG": 0.688,
      "xSLG": 0.511,
      "Barrel%": 18.2,
      "HardHit%": 45.5,
      "EV50": 96.92289,
      "BABIP": 0.6,
      "xwOBA": null,
      "wOBA": 0.51
    },
    "alejandro kirk": {
      "SLG": 0.35,
      "xSLG": 0.343,
      "Barrel%": 5.6,
      "HardHit%": 44.4,
      "EV50": 94.029336667,
      "BABIP": 0.118,
      "xwOBA": null,
      "wOBA": 0.261
    },
    "billy cook": {
      "SLG": 0.25,
      "xSLG": 0.255,
      "Barrel%": 0.0,
      "HardHit%": 50.0,
      "EV50": 94.014265,
      "BABIP": 0.5,
      "xwOBA": null,
      "wOBA": 0.227
    },
    "munetaka murakami": {
      "SLG": 0.444,
      "xSLG": 0.506,
      "Barrel%": 21.2,
      "HardHit%": 57.6,
      "EV50": 97.50803875,
      "BABIP": 0.143,
      "xwOBA": null,
      "wOBA": 0.345
    },
    "isiah kinerfalefa": {
      "SLG": 0.133,
      "xSLG": 0.158,
      "Barrel%": 0.0,
      "HardHit%": 16.7,
      "EV50": 91.117656,
      "BABIP": 0.167,
      "xwOBA": null,
      "wOBA": 0.158
    },
    "carlos correa": {
      "SLG": 0.39,
      "xSLG": 0.5,
      "Barrel%": 10.0,
      "HardHit%": 44.0,
      "EV50": 95.3845182,
      "BABIP": 0.327,
      "xwOBA": null,
      "wOBA": 0.334
    },
    "rafael marchan": {
      "SLG": 0.211,
      "xSLG": 0.199,
      "Barrel%": 6.3,
      "HardHit%": 25.0,
      "EV50": 91.872358125,
      "BABIP": 0.0,
      "xwOBA": null,
      "wOBA": 0.143
    },
    "tyler soderstrom": {
      "SLG": 0.375,
      "xSLG": 0.408,
      "Barrel%": 8.3,
      "HardHit%": 43.8,
      "EV50": 94.854672292,
      "BABIP": 0.239,
      "xwOBA": null,
      "wOBA": 0.303
    },
    "dillon dingler": {
      "SLG": 0.5,
      "xSLG": 0.605,
      "Barrel%": 15.8,
      "HardHit%": 57.9,
      "EV50": 96.150811892,
      "BABIP": 0.286,
      "xwOBA": null,
      "wOBA": 0.387
    },
    "dylan beavers": {
      "SLG": 0.326,
      "xSLG": 0.337,
      "Barrel%": 2.9,
      "HardHit%": 32.4,
      "EV50": 93.132680882,
      "BABIP": 0.273,
      "xwOBA": null,
      "wOBA": 0.291
    },
    "cj abrams": {
      "SLG": 0.695,
      "xSLG": 0.603,
      "Barrel%": 14.0,
      "HardHit%": 50.0,
      "EV50": 95.4489742,
      "BABIP": 0.341,
      "xwOBA": null,
      "wOBA": 0.483
    },
    "nasim nunez": {
      "SLG": 0.231,
      "xSLG": 0.269,
      "Barrel%": 0.0,
      "HardHit%": 17.5,
      "EV50": 91.243953421,
      "BABIP": 0.275,
      "xwOBA": null,
      "wOBA": 0.253
    },
    "brett baty": {
      "SLG": 0.309,
      "xSLG": 0.326,
      "Barrel%": 7.7,
      "HardHit%": 35.9,
      "EV50": 94.38461,
      "BABIP": 0.308,
      "xwOBA": null,
      "wOBA": 0.225
    },
    "ryan jeffers": {
      "SLG": 0.512,
      "xSLG": 0.506,
      "Barrel%": 15.6,
      "HardHit%": 50.0,
      "EV50": 97.054900625,
      "BABIP": 0.367,
      "xwOBA": null,
      "wOBA": 0.42
    },
    "pete crowarmstrong": {
      "SLG": 0.294,
      "xSLG": 0.319,
      "Barrel%": 4.3,
      "HardHit%": 44.7,
      "EV50": 95.485553488,
      "BABIP": 0.311,
      "xwOBA": null,
      "wOBA": 0.25
    },
    "jake bauers": {
      "SLG": 0.56,
      "xSLG": 0.57,
      "Barrel%": 15.4,
      "HardHit%": 56.4,
      "EV50": 97.325938205,
      "BABIP": 0.206,
      "xwOBA": null,
      "wOBA": 0.373
    },
    "tim tawa": {
      "SLG": 0.125,
      "xSLG": 0.27,
      "Barrel%": 3.7,
      "HardHit%": 29.6,
      "EV50": 92.8410804,
      "BABIP": 0.115,
      "xwOBA": null,
      "wOBA": 0.161
    },
    "yoan moncada": {
      "SLG": 0.347,
      "xSLG": 0.252,
      "Barrel%": 7.7,
      "HardHit%": 38.5,
      "EV50": 93.856843462,
      "BABIP": 0.292,
      "xwOBA": null,
      "wOBA": 0.333
    },
    "spencer steer": {
      "SLG": 0.407,
      "xSLG": 0.485,
      "Barrel%": 17.9,
      "HardHit%": 30.8,
      "EV50": 94.116545676,
      "BABIP": 0.194,
      "xwOBA": null,
      "wOBA": 0.276
    },
    "santiago espinal": {
      "SLG": 0.231,
      "xSLG": 0.361,
      "Barrel%": 0.0,
      "HardHit%": 50.0,
      "EV50": 95.039318182,
      "BABIP": 0.182,
      "xwOBA": null,
      "wOBA": 0.17
    },
    "carson benge": {
      "SLG": 0.204,
      "xSLG": 0.292,
      "Barrel%": 2.9,
      "HardHit%": 40.0,
      "EV50": 94.569443143,
      "BABIP": 0.176,
      "xwOBA": null,
      "wOBA": 0.215
    },
    "amed rosario": {
      "SLG": 0.6,
      "xSLG": 0.676,
      "Barrel%": 16.0,
      "HardHit%": 40.0,
      "EV50": 95.0430868,
      "BABIP": 0.304,
      "xwOBA": null,
      "wOBA": 0.398
    },
    "jose altuve": {
      "SLG": 0.455,
      "xSLG": 0.404,
      "Barrel%": 7.7,
      "HardHit%": 38.5,
      "EV50": 93.098220577,
      "BABIP": 0.34,
      "xwOBA": null,
      "wOBA": 0.386
    },
    "agustin ramirez": {
      "SLG": 0.381,
      "xSLG": 0.343,
      "Barrel%": 6.1,
      "HardHit%": 34.7,
      "EV50": 94.180812449,
      "BABIP": 0.313,
      "xwOBA": null,
      "wOBA": 0.324
    },
    "carlos santana": {
      "SLG": 0.125,
      "xSLG": 0.192,
      "Barrel%": 0.0,
      "HardHit%": 43.8,
      "EV50": 93.358594375,
      "BABIP": 0.125,
      "xwOBA": null,
      "wOBA": 0.139
    },
    "austin slater": {
      "SLG": 0.19,
      "xSLG": 0.229,
      "Barrel%": 0.0,
      "HardHit%": 14.3,
      "EV50": 90.863714286,
      "BABIP": 0.286,
      "xwOBA": null,
      "wOBA": 0.211
    },
    "elly de la cruz": {
      "SLG": 0.552,
      "xSLG": 0.538,
      "Barrel%": 15.2,
      "HardHit%": 52.2,
      "EV50": 97.711030233,
      "BABIP": 0.341,
      "xwOBA": null,
      "wOBA": 0.402
    },
    "ivan herrera": {
      "SLG": 0.3,
      "xSLG": 0.453,
      "Barrel%": 5.9,
      "HardHit%": 51.0,
      "EV50": 95.760461569,
      "BABIP": 0.22,
      "xwOBA": null,
      "wOBA": 0.311
    },
    "luis rengifo": {
      "SLG": 0.213,
      "xSLG": 0.305,
      "Barrel%": 7.9,
      "HardHit%": 34.2,
      "EV50": 92.752852895,
      "BABIP": 0.158,
      "xwOBA": null,
      "wOBA": 0.172
    },
    "kyle karros": {
      "SLG": 0.234,
      "xSLG": 0.374,
      "Barrel%": 5.9,
      "HardHit%": 38.2,
      "EV50": 93.961824118,
      "BABIP": 0.294,
      "xwOBA": null,
      "wOBA": 0.276
    },
    "gavin sheets": {
      "SLG": 0.44,
      "xSLG": 0.445,
      "Barrel%": 11.1,
      "HardHit%": 44.4,
      "EV50": 94.269323056,
      "BABIP": 0.265,
      "xwOBA": null,
      "wOBA": 0.303
    },
    "byron buxton": {
      "SLG": 0.462,
      "xSLG": 0.43,
      "Barrel%": 14.9,
      "HardHit%": 46.8,
      "EV50": 94.49628617,
      "BABIP": 0.295,
      "xwOBA": null,
      "wOBA": 0.338
    },
    "ronald acuna jr": {
      "SLG": 0.362,
      "xSLG": 0.554,
      "Barrel%": 16.4,
      "HardHit%": 43.6,
      "EV50": 94.909909818,
      "BABIP": 0.278,
      "xwOBA": null,
      "wOBA": 0.32
    },
    "jo adell": {
      "SLG": 0.411,
      "xSLG": 0.439,
      "Barrel%": 5.0,
      "HardHit%": 46.7,
      "EV50": 95.35606,
      "BABIP": 0.362,
      "xwOBA": null,
      "wOBA": 0.346
    },
    "rhys hoskins": {
      "SLG": 0.395,
      "xSLG": 0.33,
      "Barrel%": 14.3,
      "HardHit%": 42.9,
      "EV50": 94.297344643,
      "BABIP": 0.296,
      "xwOBA": null,
      "wOBA": 0.326
    },
    "jerar encarnacion": {
      "SLG": 0.273,
      "xSLG": 0.264,
      "Barrel%": 5.6,
      "HardHit%": 33.3,
      "EV50": 93.059362778,
      "BABIP": 0.278,
      "xwOBA": null,
      "wOBA": 0.224
    },
    "danny jansen": {
      "SLG": 0.359,
      "xSLG": 0.283,
      "Barrel%": 4.0,
      "HardHit%": 36.0,
      "EV50": 93.7977808,
      "BABIP": 0.333,
      "xwOBA": null,
      "wOBA": 0.302
    },
    "mauricio dubon": {
      "SLG": 0.532,
      "xSLG": 0.431,
      "Barrel%": 7.8,
      "HardHit%": 35.3,
      "EV50": 93.374746471,
      "BABIP": 0.388,
      "xwOBA": null,
      "wOBA": 0.404
    },
    "ben rice": {
      "SLG": 0.745,
      "xSLG": 0.68,
      "Barrel%": 23.3,
      "HardHit%": 70.0,
      "EV50": 98.313677,
      "BABIP": 0.5,
      "xwOBA": null,
      "wOBA": 0.522
    },
    "troy johnston": {
      "SLG": 0.489,
      "xSLG": 0.447,
      "Barrel%": 5.3,
      "HardHit%": 36.8,
      "EV50": 93.635027222,
      "BABIP": 0.343,
      "xwOBA": null,
      "wOBA": 0.368
    },
    "tyler stephenson": {
      "SLG": 0.324,
      "xSLG": 0.407,
      "Barrel%": 12.0,
      "HardHit%": 44.0,
      "EV50": 95.52576375,
      "BABIP": 0.174,
      "xwOBA": null,
      "wOBA": 0.292
    },
    "leo jimenez": {
      "SLG": 0.273,
      "xSLG": 0.305,
      "Barrel%": 0.0,
      "HardHit%": 27.3,
      "EV50": 92.132829091,
      "BABIP": 0.273,
      "xwOBA": null,
      "wOBA": 0.287
    },
    "alex call": {
      "SLG": 0.583,
      "xSLG": 0.472,
      "Barrel%": 0.0,
      "HardHit%": 27.3,
      "EV50": 90.624751818,
      "BABIP": 0.455,
      "xwOBA": null,
      "wOBA": 0.51
    },
    "austin martin": {
      "SLG": 0.353,
      "xSLG": 0.346,
      "Barrel%": 3.7,
      "HardHit%": 29.6,
      "EV50": 92.07920037,
      "BABIP": 0.37,
      "xwOBA": null,
      "wOBA": 0.408
    },
    "carson kelly": {
      "SLG": 0.467,
      "xSLG": 0.53,
      "Barrel%": 13.5,
      "HardHit%": 62.2,
      "EV50": 97.056954324,
      "BABIP": 0.389,
      "xwOBA": null,
      "wOBA": 0.42
    },
    "taylor ward": {
      "SLG": 0.471,
      "xSLG": 0.352,
      "Barrel%": 0.0,
      "HardHit%": 30.8,
      "EV50": 92.837170577,
      "BABIP": 0.423,
      "xwOBA": null,
      "wOBA": 0.396
    },
    "kyle manzardo": {
      "SLG": 0.229,
      "xSLG": 0.39,
      "Barrel%": 13.3,
      "HardHit%": 36.7,
      "EV50": 94.40703931,
      "BABIP": 0.207,
      "xwOBA": null,
      "wOBA": 0.228
    },
    "josh jung": {
      "SLG": 0.306,
      "xSLG": 0.377,
      "Barrel%": 0.0,
      "HardHit%": 48.6,
      "EV50": 94.348697297,
      "BABIP": 0.324,
      "xwOBA": null,
      "wOBA": 0.281
    },
    "michael massey": {
      "SLG": 0.273,
      "xSLG": 0.302,
      "Barrel%": 0.0,
      "HardHit%": 50.0,
      "EV50": 94.38825625,
      "BABIP": 0.25,
      "xwOBA": null,
      "wOBA": 0.2
    },
    "adam frazier": {
      "SLG": 0.368,
      "xSLG": 0.247,
      "Barrel%": 0.0,
      "HardHit%": 28.6,
      "EV50": 91.330663846,
      "BABIP": 0.462,
      "xwOBA": null,
      "wOBA": 0.404
    },
    "mark vientos": {
      "SLG": 0.341,
      "xSLG": 0.344,
      "Barrel%": 2.9,
      "HardHit%": 35.3,
      "EV50": 93.068958824,
      "BABIP": 0.273,
      "xwOBA": null,
      "wOBA": 0.266
    },
    "eloy jimenez": {
      "SLG": 0.286,
      "xSLG": 0.277,
      "Barrel%": 0.0,
      "HardHit%": 20.0,
      "EV50": 91.00549,
      "BABIP": 0.4,
      "xwOBA": null,
      "wOBA": 0.316
    },
    "alex freeland": {
      "SLG": 0.31,
      "xSLG": 0.353,
      "Barrel%": 6.9,
      "HardHit%": 44.8,
      "EV50": 95.236215714,
      "BABIP": 0.259,
      "xwOBA": null,
      "wOBA": 0.263
    },
    "adley rutschman": {
      "SLG": 0.471,
      "xSLG": 0.322,
      "Barrel%": 3.6,
      "HardHit%": 42.9,
      "EV50": 94.07614,
      "BABIP": 0.357,
      "xwOBA": null,
      "wOBA": 0.384
    },
    "jacob wilson": {
      "SLG": 0.284,
      "xSLG": 0.316,
      "Barrel%": 0.0,
      "HardHit%": 35.1,
      "EV50": 92.449046429,
      "BABIP": 0.281,
      "xwOBA": null,
      "wOBA": 0.241
    },
    "denzel clarke": {
      "SLG": 0.186,
      "xSLG": 0.205,
      "Barrel%": 4.0,
      "HardHit%": 52.0,
      "EV50": 96.862243478,
      "BABIP": 0.292,
      "xwOBA": null,
      "wOBA": 0.193
    },
    "austin hays": {
      "SLG": 0.344,
      "xSLG": 0.347,
      "Barrel%": 5.0,
      "HardHit%": 55.0,
      "EV50": 95.3766265,
      "BABIP": 0.316,
      "xwOBA": null,
      "wOBA": 0.249
    },
    "jt realmuto": {
      "SLG": 0.405,
      "xSLG": 0.366,
      "Barrel%": 3.1,
      "HardHit%": 40.6,
      "EV50": 93.871794375,
      "BABIP": 0.355,
      "xwOBA": null,
      "wOBA": 0.366
    },
    "cal raleigh": {
      "SLG": 0.261,
      "xSLG": 0.371,
      "Barrel%": 9.1,
      "HardHit%": 25.0,
      "EV50": 92.193437727,
      "BABIP": 0.19,
      "xwOBA": null,
      "wOBA": 0.23
    },
    "ramon urias": {
      "SLG": 0.5,
      "xSLG": 0.505,
      "Barrel%": 16.7,
      "HardHit%": 50.0,
      "EV50": 95.386240833,
      "BABIP": 0.227,
      "xwOBA": null,
      "wOBA": 0.365
    },
    "nick fortes": {
      "SLG": 0.457,
      "xSLG": 0.411,
      "Barrel%": 2.4,
      "HardHit%": 41.5,
      "EV50": 94.4868055,
      "BABIP": 0.325,
      "xwOBA": null,
      "wOBA": 0.353
    },
    "brandon marsh": {
      "SLG": 0.475,
      "xSLG": 0.483,
      "Barrel%": 6.5,
      "HardHit%": 47.8,
      "EV50": 94.913992826,
      "BABIP": 0.364,
      "xwOBA": null,
      "wOBA": 0.356
    },
    "pedro pages": {
      "SLG": 0.323,
      "xSLG": 0.352,
      "Barrel%": 4.2,
      "HardHit%": 41.7,
      "EV50": 94.095875,
      "BABIP": 0.217,
      "xwOBA": null,
      "wOBA": 0.264
    },
    "jake cronenworth": {
      "SLG": 0.218,
      "xSLG": 0.372,
      "Barrel%": 4.7,
      "HardHit%": 34.9,
      "EV50": 93.874089268,
      "BABIP": 0.167,
      "xwOBA": null,
      "wOBA": 0.223
    },
    "dylan carlson": {
      "SLG": 0.0,
      "xSLG": 0.096,
      "Barrel%": 0.0,
      "HardHit%": 0.0,
      "EV50": 88.08244,
      "BABIP": 0.0,
      "xwOBA": null,
      "wOBA": 0.0
    },
    "luisangel acuna": {
      "SLG": 0.18,
      "xSLG": 0.266,
      "Barrel%": 2.2,
      "HardHit%": 33.3,
      "EV50": 93.20334,
      "BABIP": 0.205,
      "xwOBA": null,
      "wOBA": 0.182
    },
    "max muncy": {
      "SLG": 0.446,
      "xSLG": 0.54,
      "Barrel%": 17.6,
      "HardHit%": 55.9,
      "EV50": 96.318070294,
      "BABIP": 0.3,
      "xwOBA": null,
      "wOBA": 0.337
    },
    "trent grisham": {
      "SLG": 0.327,
      "xSLG": 0.459,
      "Barrel%": 12.8,
      "HardHit%": 64.1,
      "EV50": 96.432399231,
      "BABIP": 0.162,
      "xwOBA": null,
      "wOBA": 0.308
    },
    "leo rivas": {
      "SLG": 0.211,
      "xSLG": 0.162,
      "Barrel%": 0.0,
      "HardHit%": 4.5,
      "EV50": 90.268555455,
      "BABIP": 0.273,
      "xwOBA": null,
      "wOBA": 0.268
    },
    "victor scott ii": {
      "SLG": 0.289,
      "xSLG": 0.31,
      "Barrel%": 0.0,
      "HardHit%": 22.5,
      "EV50": 92.118515313,
      "BABIP": 0.343,
      "xwOBA": null,
      "wOBA": 0.256
    },
    "bryan reynolds": {
      "SLG": 0.477,
      "xSLG": 0.516,
      "Barrel%": 10.9,
      "HardHit%": 50.0,
      "EV50": 96.546523261,
      "BABIP": 0.372,
      "xwOBA": null,
      "wOBA": 0.384
    },
    "corey seager": {
      "SLG": 0.41,
      "xSLG": 0.429,
      "Barrel%": 15.9,
      "HardHit%": 45.5,
      "EV50": 95.210309545,
      "BABIP": 0.2,
      "xwOBA": null,
      "wOBA": 0.313
    },
    "jeremiah jackson": {
      "SLG": 0.563,
      "xSLG": 0.497,
      "Barrel%": 10.5,
      "HardHit%": 28.9,
      "EV50": 93.532752162,
      "BABIP": 0.371,
      "xwOBA": null,
      "wOBA": 0.393
    },
    "matt vierling": {
      "SLG": 0.348,
      "xSLG": 0.247,
      "Barrel%": 5.6,
      "HardHit%": 33.3,
      "EV50": 91.874855556,
      "BABIP": 0.176,
      "xwOBA": null,
      "wOBA": 0.237
    },
    "jac caglianone": {
      "SLG": 0.313,
      "xSLG": 0.346,
      "Barrel%": 12.9,
      "HardHit%": 51.6,
      "EV50": 97.690825484,
      "BABIP": 0.355,
      "xwOBA": null,
      "wOBA": 0.294
    },
    "jacob young": {
      "SLG": 0.469,
      "xSLG": 0.466,
      "Barrel%": 7.1,
      "HardHit%": 40.5,
      "EV50": 93.75207878,
      "BABIP": 0.282,
      "xwOBA": null,
      "wOBA": 0.337
    },
    "salvador perez": {
      "SLG": 0.286,
      "xSLG": 0.385,
      "Barrel%": 11.5,
      "HardHit%": 40.4,
      "EV50": 94.767236923,
      "BABIP": 0.16,
      "xwOBA": null,
      "wOBA": 0.226
    },
    "brandon lockridge": {
      "SLG": 0.325,
      "xSLG": 0.269,
      "Barrel%": 3.1,
      "HardHit%": 31.3,
      "EV50": 92.903394667,
      "BABIP": 0.355,
      "xwOBA": null,
      "wOBA": 0.31
    },
    "zach mckinstry": {
      "SLG": 0.317,
      "xSLG": 0.299,
      "Barrel%": 3.1,
      "HardHit%": 25.0,
      "EV50": 91.394308125,
      "BABIP": 0.226,
      "xwOBA": null,
      "wOBA": 0.259
    },
    "jp crawford": {
      "SLG": 0.226,
      "xSLG": 0.393,
      "Barrel%": 8.7,
      "HardHit%": 34.8,
      "EV50": 93.881280435,
      "BABIP": 0.261,
      "xwOBA": null,
      "wOBA": 0.335
    },
    "bo naylor": {
      "SLG": 0.143,
      "xSLG": 0.453,
      "Barrel%": 14.8,
      "HardHit%": 51.9,
      "EV50": 95.483145185,
      "BABIP": 0.185,
      "xwOBA": null,
      "wOBA": 0.19
    },
    "adrian del castillo": {
      "SLG": 0.381,
      "xSLG": 0.339,
      "Barrel%": 0.0,
      "HardHit%": 28.6,
      "EV50": 92.648363077,
      "BABIP": 0.5,
      "xwOBA": null,
      "wOBA": 0.322
    },
    "isaac paredes": {
      "SLG": 0.319,
      "xSLG": 0.286,
      "Barrel%": 0.0,
      "HardHit%": 27.8,
      "EV50": 92.456964722,
      "BABIP": 0.306,
      "xwOBA": null,
      "wOBA": 0.316
    },
    "tristan peters": {
      "SLG": 0.27,
      "xSLG": 0.225,
      "Barrel%": 0.0,
      "HardHit%": 8.3,
      "EV50": 90.646549474,
      "BABIP": 0.375,
      "xwOBA": null,
      "wOBA": 0.268
    },
    "harrison bader": {
      "SLG": 0.192,
      "xSLG": 0.335,
      "Barrel%": 8.3,
      "HardHit%": 38.9,
      "EV50": 93.322891667,
      "BABIP": 0.143,
      "xwOBA": null,
      "wOBA": 0.154
    },
    "ian happ": {
      "SLG": 0.484,
      "xSLG": 0.464,
      "Barrel%": 18.4,
      "HardHit%": 50.0,
      "EV50": 95.774533421,
      "BABIP": 0.294,
      "xwOBA": null,
      "wOBA": 0.349
    },
    "michael harris ii": {
      "SLG": 0.362,
      "xSLG": 0.569,
      "Barrel%": 15.6,
      "HardHit%": 46.7,
      "EV50": 95.957478182,
      "BABIP": 0.279,
      "xwOBA": null,
      "wOBA": 0.289
    },
    "vaughn grissom": {
      "SLG": 0.3,
      "xSLG": 0.359,
      "Barrel%": 0.0,
      "HardHit%": 33.3,
      "EV50": 93.29735,
      "BABIP": 0.333,
      "xwOBA": null,
      "wOBA": 0.374
    },
    "jonathan aranda": {
      "SLG": 0.413,
      "xSLG": 0.48,
      "Barrel%": 10.2,
      "HardHit%": 49.0,
      "EV50": 95.213190408,
      "BABIP": 0.239,
      "xwOBA": null,
      "wOBA": 0.319
    },
    "wyatt langford": {
      "SLG": 0.321,
      "xSLG": 0.361,
      "Barrel%": 7.1,
      "HardHit%": 40.5,
      "EV50": 94.661105714,
      "BABIP": 0.195,
      "xwOBA": null,
      "wOBA": 0.225
    },
    "jose fermin": {
      "SLG": 0.231,
      "xSLG": 0.17,
      "Barrel%": 0.0,
      "HardHit%": 20.0,
      "EV50": 91.420332,
      "BABIP": 0.3,
      "xwOBA": null,
      "wOBA": 0.26
    },
    "tommy pham": {
      "SLG": 0.0,
      "xSLG": 0.373,
      "Barrel%": 0.0,
      "HardHit%": 100.0,
      "EV50": 104.819505,
      "BABIP": 0.0,
      "xwOBA": null,
      "wOBA": 0.0
    },
    "xavier edwards": {
      "SLG": 0.493,
      "xSLG": 0.402,
      "Barrel%": 3.4,
      "HardHit%": 42.4,
      "EV50": 93.260547586,
      "BABIP": 0.386,
      "xwOBA": null,
      "wOBA": 0.402
    },
    "victor robles": {
      "SLG": 0.308,
      "xSLG": 0.366,
      "Barrel%": 10.0,
      "HardHit%": 20.0,
      "EV50": 90.740758,
      "BABIP": 0.3,
      "xwOBA": null,
      "wOBA": 0.24
    },
    "jarren duran": {
      "SLG": 0.291,
      "xSLG": 0.379,
      "Barrel%": 12.8,
      "HardHit%": 41.0,
      "EV50": 95.724967568,
      "BABIP": 0.237,
      "xwOBA": null,
      "wOBA": 0.266
    },
    "juan brito": {
      "SLG": 0.348,
      "xSLG": 0.327,
      "Barrel%": 0.0,
      "HardHit%": 27.8,
      "EV50": 92.535172222,
      "BABIP": 0.333,
      "xwOBA": null,
      "wOBA": 0.306
    },
    "nolan schanuel": {
      "SLG": 0.344,
      "xSLG": 0.371,
      "Barrel%": 1.9,
      "HardHit%": 34.6,
      "EV50": 92.692291923,
      "BABIP": 0.22,
      "xwOBA": null,
      "wOBA": 0.296
    },
    "dane myers": {
      "SLG": 0.261,
      "xSLG": 0.584,
      "Barrel%": 5.3,
      "HardHit%": 31.6,
      "EV50": 93.219826111,
      "BABIP": 0.316,
      "xwOBA": null,
      "wOBA": 0.275
    },
    "ty france": {
      "SLG": 0.5,
      "xSLG": 0.724,
      "Barrel%": 18.8,
      "HardHit%": 56.3,
      "EV50": 96.3554425,
      "BABIP": 0.267,
      "xwOBA": null,
      "wOBA": 0.379
    },
    "brayan rocchio": {
      "SLG": 0.333,
      "xSLG": 0.389,
      "Barrel%": 4.3,
      "HardHit%": 34.0,
      "EV50": 93.704554,
      "BABIP": 0.205,
      "xwOBA": null,
      "wOBA": 0.318
    },
    "patrick wisdom": {
      "SLG": 0.0,
      "xSLG": 0.0,
      "Barrel%": null,
      "HardHit%": null,
      "EV50": null,
      "BABIP": 0.0,
      "xwOBA": null,
      "wOBA": 0.0
    },
    "hunter goodman": {
      "SLG": 0.475,
      "xSLG": 0.371,
      "Barrel%": 9.1,
      "HardHit%": 48.5,
      "EV50": 96.142893939,
      "BABIP": 0.379,
      "xwOBA": null,
      "wOBA": 0.356
    },
    "andres gimenez": {
      "SLG": 0.483,
      "xSLG": 0.377,
      "Barrel%": 6.0,
      "HardHit%": 30.0,
      "EV50": 92.923559184,
      "BABIP": 0.283,
      "xwOBA": null,
      "wOBA": 0.357
    },
    "luis garcia jr": {
      "SLG": 0.4,
      "xSLG": 0.476,
      "Barrel%": 8.5,
      "HardHit%": 42.6,
      "EV50": 95.052016667,
      "BABIP": 0.283,
      "xwOBA": null,
      "wOBA": 0.302
    },
    "ryan mcmahon": {
      "SLG": 0.128,
      "xSLG": 0.245,
      "Barrel%": 8.3,
      "HardHit%": 54.2,
      "EV50": 95.321188261,
      "BABIP": 0.208,
      "xwOBA": null,
      "wOBA": 0.218
    },
    "griffin conine": {
      "SLG": 0.591,
      "xSLG": 0.773,
      "Barrel%": 25.0,
      "HardHit%": 62.5,
      "EV50": 98.354698125,
      "BABIP": 0.286,
      "xwOBA": null,
      "wOBA": 0.416
    },
    "david fry": {
      "SLG": 0.231,
      "xSLG": 0.284,
      "Barrel%": 13.3,
      "HardHit%": 46.7,
      "EV50": 94.178246667,
      "BABIP": 0.333,
      "xwOBA": null,
      "wOBA": 0.274
    },
    "david hamilton": {
      "SLG": 0.188,
      "xSLG": 0.269,
      "Barrel%": 3.6,
      "HardHit%": 25.0,
      "EV50": 91.934861667,
      "BABIP": 0.231,
      "xwOBA": null,
      "wOBA": 0.3
    },
    "connor norby": {
      "SLG": 0.451,
      "xSLG": 0.379,
      "Barrel%": 10.5,
      "HardHit%": 36.8,
      "EV50": 92.550128421,
      "BABIP": 0.306,
      "xwOBA": null,
      "wOBA": 0.371
    },
    "tyler tolbert": {
      "SLG": 0.0,
      "xSLG": 0.211,
      "Barrel%": 0.0,
      "HardHit%": 33.3,
      "EV50": 92.94304,
      "BABIP": 0.0,
      "xwOBA": null,
      "wOBA": 0.0
    },
    "tristan gray": {
      "SLG": 0.538,
      "xSLG": 0.383,
      "Barrel%": 15.8,
      "HardHit%": 36.8,
      "EV50": 94.247417222,
      "BABIP": 0.313,
      "xwOBA": null,
      "wOBA": 0.377
    },
    "ceddanne rafaela": {
      "SLG": 0.383,
      "xSLG": 0.385,
      "Barrel%": 7.9,
      "HardHit%": 36.8,
      "EV50": 93.314244444,
      "BABIP": 0.351,
      "xwOBA": null,
      "wOBA": 0.346
    },
    "jorge barrosa": {
      "SLG": 0.439,
      "xSLG": 0.264,
      "Barrel%": 7.7,
      "HardHit%": 23.1,
      "EV50": 91.623948696,
      "BABIP": 0.4,
      "xwOBA": null,
      "wOBA": 0.325
    },
    "ezequiel tovar": {
      "SLG": 0.409,
      "xSLG": 0.473,
      "Barrel%": 8.7,
      "HardHit%": 47.8,
      "EV50": 94.981648696,
      "BABIP": 0.356,
      "xwOBA": null,
      "wOBA": 0.312
    },
    "otto kemp": {
      "SLG": 0.154,
      "xSLG": 0.264,
      "Barrel%": 0.0,
      "HardHit%": 16.7,
      "EV50": 90.253815,
      "BABIP": 0.333,
      "xwOBA": null,
      "wOBA": 0.218
    },
    "oswald peraza": {
      "SLG": 0.511,
      "xSLG": 0.419,
      "Barrel%": 8.8,
      "HardHit%": 41.2,
      "EV50": 94.721781563,
      "BABIP": 0.3,
      "xwOBA": null,
      "wOBA": 0.37
    },
    "bryson stott": {
      "SLG": 0.222,
      "xSLG": 0.387,
      "Barrel%": 6.8,
      "HardHit%": 50.0,
      "EV50": 94.515429545,
      "BABIP": 0.25,
      "xwOBA": null,
      "wOBA": 0.237
    },
    "miguel vargas": {
      "SLG": 0.315,
      "xSLG": 0.354,
      "Barrel%": 9.8,
      "HardHit%": 41.5,
      "EV50": 94.006981463,
      "BABIP": 0.2,
      "xwOBA": null,
      "wOBA": 0.297
    },
    "starling marte": {
      "SLG": 0.333,
      "xSLG": 0.325,
      "Barrel%": 18.2,
      "HardHit%": 54.5,
      "EV50": 98.580406364,
      "BABIP": 0.364,
      "xwOBA": null,
      "wOBA": 0.245
    },
    "giancarlo stanton": {
      "SLG": 0.397,
      "xSLG": 0.424,
      "Barrel%": 12.5,
      "HardHit%": 35.0,
      "EV50": 95.66333625,
      "BABIP": 0.41,
      "xwOBA": null,
      "wOBA": 0.345
    },
    "roman anthony": {
      "SLG": 0.361,
      "xSLG": 0.431,
      "Barrel%": 11.9,
      "HardHit%": 45.2,
      "EV50": 96.171512195,
      "BABIP": 0.317,
      "xwOBA": null,
      "wOBA": 0.318
    },
    "addison barger": {
      "SLG": 0.105,
      "xSLG": 0.184,
      "Barrel%": 0.0,
      "HardHit%": 50.0,
      "EV50": 95.018167857,
      "BABIP": 0.071,
      "xwOBA": null,
      "wOBA": 0.149
    },
    "luis campusano": {
      "SLG": 0.667,
      "xSLG": 0.489,
      "Barrel%": 21.4,
      "HardHit%": 50.0,
      "EV50": 95.676210714,
      "BABIP": 0.462,
      "xwOBA": null,
      "wOBA": 0.446
    },
    "marcelo mayer": {
      "SLG": 0.326,
      "xSLG": 0.31,
      "Barrel%": 12.5,
      "HardHit%": 43.8,
      "EV50": 93.789154375,
      "BABIP": 0.226,
      "xwOBA": null,
      "wOBA": 0.269
    },
    "will smith": {
      "SLG": 0.431,
      "xSLG": 0.491,
      "Barrel%": 12.2,
      "HardHit%": 36.6,
      "EV50": 93.802235122,
      "BABIP": 0.333,
      "xwOBA": null,
      "wOBA": 0.375
    },
    "colson montgomery": {
      "SLG": 0.39,
      "xSLG": 0.317,
      "Barrel%": 10.3,
      "HardHit%": 28.2,
      "EV50": 92.689617436,
      "BABIP": 0.222,
      "xwOBA": null,
      "wOBA": 0.307
    },
    "jahmai jones": {
      "SLG": 0.0,
      "xSLG": 0.225,
      "Barrel%": 0.0,
      "HardHit%": 33.3,
      "EV50": 92.00087,
      "BABIP": 0.0,
      "xwOBA": null,
      "wOBA": 0.0
    },
    "alec bohm": {
      "SLG": 0.22,
      "xSLG": 0.297,
      "Barrel%": 0.0,
      "HardHit%": 39.6,
      "EV50": 93.928664167,
      "BABIP": 0.17,
      "xwOBA": null,
      "wOBA": 0.213
    },
    "marcell ozuna": {
      "SLG": 0.128,
      "xSLG": 0.269,
      "Barrel%": 2.9,
      "HardHit%": 37.1,
      "EV50": 93.522561765,
      "BABIP": 0.143,
      "xwOBA": null,
      "wOBA": 0.163
    },
    "yohel pozo": {
      "SLG": 0.2,
      "xSLG": 0.292,
      "Barrel%": 0.0,
      "HardHit%": 40.0,
      "EV50": 94.008094667,
      "BABIP": 0.133,
      "xwOBA": null,
      "wOBA": 0.147
    },
    "josh bell": {
      "SLG": 0.483,
      "xSLG": 0.444,
      "Barrel%": 11.4,
      "HardHit%": 47.7,
      "EV50": 94.194064545,
      "BABIP": 0.293,
      "xwOBA": null,
      "wOBA": 0.375
    },
    "colton cowser": {
      "SLG": 0.257,
      "xSLG": 0.341,
      "Barrel%": 11.1,
      "HardHit%": 40.7,
      "EV50": 94.177971923,
      "BABIP": 0.308,
      "xwOBA": null,
      "wOBA": 0.284
    },
    "yainer diaz": {
      "SLG": 0.294,
      "xSLG": 0.277,
      "Barrel%": 2.3,
      "HardHit%": 27.3,
      "EV50": 92.990719091,
      "BABIP": 0.233,
      "xwOBA": null,
      "wOBA": 0.25
    },
    "austin hedges": {
      "SLG": 0.45,
      "xSLG": 0.391,
      "Barrel%": 0.0,
      "HardHit%": 50.0,
      "EV50": 94.120524444,
      "BABIP": 0.389,
      "xwOBA": null,
      "wOBA": 0.372
    },
    "liam hicks": {
      "SLG": 0.51,
      "xSLG": 0.452,
      "Barrel%": 6.1,
      "HardHit%": 38.8,
      "EV50": 93.618289796,
      "BABIP": 0.283,
      "xwOBA": null,
      "wOBA": 0.382
    },
    "javier baez": {
      "SLG": 0.439,
      "xSLG": 0.389,
      "Barrel%": 3.0,
      "HardHit%": 39.4,
      "EV50": 93.383523939,
      "BABIP": 0.344,
      "xwOBA": null,
      "wOBA": 0.335
    },
    "jorbit vivas": {
      "SLG": 0.367,
      "xSLG": 0.309,
      "Barrel%": 0.0,
      "HardHit%": 13.8,
      "EV50": 90.268152963,
      "BABIP": 0.37,
      "xwOBA": null,
      "wOBA": 0.383
    },
    "mookie betts": {
      "SLG": 0.429,
      "xSLG": 0.4,
      "Barrel%": 8.3,
      "HardHit%": 33.3,
      "EV50": 93.671050833,
      "BABIP": 0.136,
      "xwOBA": null,
      "wOBA": 0.319
    },
    "joey loperfido": {
      "SLG": 0.396,
      "xSLG": 0.29,
      "Barrel%": 2.9,
      "HardHit%": 41.2,
      "EV50": 93.838279412,
      "BABIP": 0.412,
      "xwOBA": null,
      "wOBA": 0.344
    },
    "angel martinez": {
      "SLG": 0.51,
      "xSLG": 0.437,
      "Barrel%": 6.5,
      "HardHit%": 41.3,
      "EV50": 95.277387045,
      "BABIP": 0.326,
      "xwOBA": null,
      "wOBA": 0.395
    },
    "francisco lindor": {
      "SLG": 0.306,
      "xSLG": 0.407,
      "Barrel%": 8.6,
      "HardHit%": 37.9,
      "EV50": 93.685290172,
      "BABIP": 0.228,
      "xwOBA": null,
      "wOBA": 0.285
    },
    "matt shaw": {
      "SLG": 0.356,
      "xSLG": 0.415,
      "Barrel%": 8.1,
      "HardHit%": 32.4,
      "EV50": 92.463521389,
      "BABIP": 0.206,
      "xwOBA": null,
      "wOBA": 0.268
    },
    "carlos narvaez": {
      "SLG": 0.195,
      "xSLG": 0.331,
      "Barrel%": 7.1,
      "HardHit%": 50.0,
      "EV50": 95.141795185,
      "BABIP": 0.296,
      "xwOBA": null,
      "wOBA": 0.19
    },
    "freddy fermin": {
      "SLG": 0.226,
      "xSLG": 0.272,
      "Barrel%": 0.0,
      "HardHit%": 37.5,
      "EV50": 92.81856375,
      "BABIP": 0.208,
      "xwOBA": null,
      "wOBA": 0.241
    },
    "brice turang": {
      "SLG": 0.604,
      "xSLG": 0.522,
      "Barrel%": 10.3,
      "HardHit%": 48.7,
      "EV50": 96.172529459,
      "BABIP": 0.4,
      "xwOBA": null,
      "wOBA": 0.456
    },
    "andrew vaughn": {
      "SLG": 0.25,
      "xSLG": 0.265,
      "Barrel%": 0.0,
      "HardHit%": 0.0,
      "EV50": 91.308375,
      "BABIP": 0.25,
      "xwOBA": null,
      "wOBA": 0.227
    },
    "noelvi marte": {
      "SLG": 0.138,
      "xSLG": 0.149,
      "Barrel%": 0.0,
      "HardHit%": 31.6,
      "EV50": 92.962525263,
      "BABIP": 0.211,
      "xwOBA": null,
      "wOBA": 0.163
    },
    "bryce harper": {
      "SLG": 0.484,
      "xSLG": 0.613,
      "Barrel%": 15.1,
      "HardHit%": 39.6,
      "EV50": 94.396451887,
      "BABIP": 0.26,
      "xwOBA": null,
      "wOBA": 0.378
    },
    "hunter feduccia": {
      "SLG": 0.2,
      "xSLG": 0.234,
      "Barrel%": 0.0,
      "HardHit%": 28.6,
      "EV50": 92.859418571,
      "BABIP": 0.429,
      "xwOBA": null,
      "wOBA": 0.27
    },
    "josh naylor": {
      "SLG": 0.224,
      "xSLG": 0.39,
      "Barrel%": 7.1,
      "HardHit%": 35.7,
      "EV50": 93.324984364,
      "BABIP": 0.13,
      "xwOBA": null,
      "wOBA": 0.204
    },
    "randal grichuk": {
      "SLG": 0.125,
      "xSLG": 0.564,
      "Barrel%": 44.4,
      "HardHit%": 55.6,
      "EV50": 97.18604,
      "BABIP": 0.111,
      "xwOBA": null,
      "wOBA": 0.118
    },
    "thomas saggese": {
      "SLG": 0.256,
      "xSLG": 0.261,
      "Barrel%": 3.4,
      "HardHit%": 31.0,
      "EV50": 93.332665172,
      "BABIP": 0.31,
      "xwOBA": null,
      "wOBA": 0.251
    },
    "eugenio suarez": {
      "SLG": 0.333,
      "xSLG": 0.373,
      "Barrel%": 10.3,
      "HardHit%": 23.1,
      "EV50": 93.674872222,
      "BABIP": 0.297,
      "xwOBA": null,
      "wOBA": 0.292
    },
    "jakob marsee": {
      "SLG": 0.246,
      "xSLG": 0.265,
      "Barrel%": 2.0,
      "HardHit%": 39.2,
      "EV50": 93.4912204,
      "BABIP": 0.235,
      "xwOBA": null,
      "wOBA": 0.255
    },
    "nathan church": {
      "SLG": 0.229,
      "xSLG": 0.287,
      "Barrel%": 8.0,
      "HardHit%": 32.0,
      "EV50": 92.6900108,
      "BABIP": 0.167,
      "xwOBA": null,
      "wOBA": 0.19
    },
    "nick castellanos": {
      "SLG": 0.286,
      "xSLG": 0.475,
      "Barrel%": 6.9,
      "HardHit%": 44.8,
      "EV50": 94.530467586,
      "BABIP": 0.241,
      "xwOBA": null,
      "wOBA": 0.242
    },
    "vladimir guerrero jr": {
      "SLG": 0.448,
      "xSLG": 0.517,
      "Barrel%": 15.4,
      "HardHit%": 48.1,
      "EV50": 96.421010962,
      "BABIP": 0.353,
      "xwOBA": null,
      "wOBA": 0.4
    },
    "alex bregman": {
      "SLG": 0.343,
      "xSLG": 0.372,
      "Barrel%": 6.7,
      "HardHit%": 46.7,
      "EV50": 94.440779167,
      "BABIP": 0.259,
      "xwOBA": null,
      "wOBA": 0.303
    },
    "rafael devers": {
      "SLG": 0.318,
      "xSLG": 0.399,
      "Barrel%": 10.9,
      "HardHit%": 47.8,
      "EV50": 95.608783261,
      "BABIP": 0.273,
      "xwOBA": null,
      "wOBA": 0.262
    },
    "daylen lile": {
      "SLG": 0.338,
      "xSLG": 0.418,
      "Barrel%": 3.2,
      "HardHit%": 40.3,
      "EV50": 93.194305806,
      "BABIP": 0.333,
      "xwOBA": null,
      "wOBA": 0.301
    },
    "kerry carpenter": {
      "SLG": 0.417,
      "xSLG": 0.382,
      "Barrel%": 14.3,
      "HardHit%": 53.6,
      "EV50": 95.687242857,
      "BABIP": 0.28,
      "xwOBA": null,
      "wOBA": 0.33
    },
    "nick allen": {
      "SLG": 0.188,
      "xSLG": 0.205,
      "Barrel%": 0.0,
      "HardHit%": 33.3,
      "EV50": 93.297205,
      "BABIP": 0.25,
      "xwOBA": null,
      "wOBA": 0.231
    },
    "keibert ruiz": {
      "SLG": 0.355,
      "xSLG": 0.31,
      "Barrel%": 7.1,
      "HardHit%": 35.7,
      "EV50": 92.249321429,
      "BABIP": 0.185,
      "xwOBA": null,
      "wOBA": 0.247
    },
    "brandon nimmo": {
      "SLG": 0.551,
      "xSLG": 0.443,
      "Barrel%": 9.4,
      "HardHit%": 39.6,
      "EV50": 94.296531887,
      "BABIP": 0.4,
      "xwOBA": null,
      "wOBA": 0.415
    },
    "mike yastrzemski": {
      "SLG": 0.268,
      "xSLG": 0.242,
      "Barrel%": 2.6,
      "HardHit%": 38.5,
      "EV50": 94.028506053,
      "BABIP": 0.282,
      "xwOBA": null,
      "wOBA": 0.269
    },
    "austin wynns": {
      "SLG": 0.167,
      "xSLG": 0.657,
      "Barrel%": 16.7,
      "HardHit%": 25.0,
      "EV50": 93.05242,
      "BABIP": 0.182,
      "xwOBA": null,
      "wOBA": 0.195
    },
    "ildemaro vargas": {
      "SLG": 0.667,
      "xSLG": 0.542,
      "Barrel%": 8.6,
      "HardHit%": 37.1,
      "EV50": 93.521507059,
      "BABIP": 0.424,
      "xwOBA": null,
      "wOBA": 0.469
    },
    "daniel susac": {
      "SLG": 0.75,
      "xSLG": 0.605,
      "Barrel%": 9.1,
      "HardHit%": 45.5,
      "EV50": 94.411808182,
      "BABIP": 0.636,
      "xwOBA": null,
      "wOBA": 0.601
    },
    "jake rogers": {
      "SLG": 0.167,
      "xSLG": 0.2,
      "Barrel%": 14.3,
      "HardHit%": 42.9,
      "EV50": 94.147085714,
      "BABIP": 0.143,
      "xwOBA": null,
      "wOBA": 0.157
    },
    "willson contreras": {
      "SLG": 0.491,
      "xSLG": 0.507,
      "Barrel%": 15.8,
      "HardHit%": 42.1,
      "EV50": 96.0816025,
      "BABIP": 0.4,
      "xwOBA": null,
      "wOBA": 0.426
    },
    "luke keaschall": {
      "SLG": 0.304,
      "xSLG": 0.355,
      "Barrel%": 3.4,
      "HardHit%": 25.4,
      "EV50": 92.215666552,
      "BABIP": 0.259,
      "xwOBA": null,
      "wOBA": 0.274
    },
    "jordan beck": {
      "SLG": 0.257,
      "xSLG": 0.326,
      "Barrel%": 3.7,
      "HardHit%": 33.3,
      "EV50": 93.284213333,
      "BABIP": 0.154,
      "xwOBA": null,
      "wOBA": 0.218
    },
    "andruw monasterio": {
      "SLG": 0.214,
      "xSLG": 0.249,
      "Barrel%": 11.1,
      "HardHit%": 55.6,
      "EV50": 94.986908889,
      "BABIP": 0.222,
      "xwOBA": null,
      "wOBA": 0.255
    },
    "evan carter": {
      "SLG": 0.396,
      "xSLG": 0.437,
      "Barrel%": 12.1,
      "HardHit%": 48.5,
      "EV50": 94.656871212,
      "BABIP": 0.258,
      "xwOBA": null,
      "wOBA": 0.341
    },
    "matt olson": {
      "SLG": 0.592,
      "xSLG": 0.548,
      "Barrel%": 18.8,
      "HardHit%": 45.8,
      "EV50": 96.244469375,
      "BABIP": 0.386,
      "xwOBA": null,
      "wOBA": 0.418
    },
    "brady house": {
      "SLG": 0.433,
      "xSLG": 0.405,
      "Barrel%": 9.8,
      "HardHit%": 41.5,
      "EV50": 93.860899268,
      "BABIP": 0.359,
      "xwOBA": null,
      "wOBA": 0.339
    },
    "hyeseong kim": {
      "SLG": 0.357,
      "xSLG": 0.372,
      "Barrel%": 10.0,
      "HardHit%": 30.0,
      "EV50": 93.686858,
      "BABIP": 0.4,
      "xwOBA": null,
      "wOBA": 0.362
    },
    "otto lopez": {
      "SLG": 0.508,
      "xSLG": 0.501,
      "Barrel%": 13.2,
      "HardHit%": 54.7,
      "EV50": 96.338221132,
      "BABIP": 0.353,
      "xwOBA": null,
      "wOBA": 0.388
    },
    "jeimer candelario": {
      "SLG": 0.222,
      "xSLG": 0.212,
      "Barrel%": 0.0,
      "HardHit%": 40.0,
      "EV50": 93.916024,
      "BABIP": 0.2,
      "xwOBA": null,
      "wOBA": 0.202
    },
    "mike trout": {
      "SLG": 0.508,
      "xSLG": 0.727,
      "Barrel%": 28.3,
      "HardHit%": 45.7,
      "EV50": 96.774715111,
      "BABIP": 0.22,
      "xwOBA": null,
      "wOBA": 0.397
    },
    "austin riley": {
      "SLG": 0.258,
      "xSLG": 0.333,
      "Barrel%": 5.8,
      "HardHit%": 40.4,
      "EV50": 94.338970385,
      "BABIP": 0.269,
      "xwOBA": null,
      "wOBA": 0.271
    },
    "ryan ritter": {
      "SLG": 0.143,
      "xSLG": 0.214,
      "Barrel%": 0.0,
      "HardHit%": 25.0,
      "EV50": 91.276415,
      "BABIP": 0.25,
      "xwOBA": null,
      "wOBA": 0.13
    },
    "miguel rojas": {
      "SLG": 0.429,
      "xSLG": 0.407,
      "Barrel%": 4.3,
      "HardHit%": 43.5,
      "EV50": 94.313379565,
      "BABIP": 0.435,
      "xwOBA": null,
      "wOBA": 0.375
    },
    "juan soto": {
      "SLG": 0.516,
      "xSLG": 0.43,
      "Barrel%": 8.0,
      "HardHit%": 28.0,
      "EV50": 93.947794167,
      "BABIP": 0.417,
      "xwOBA": null,
      "wOBA": 0.406
    },
    "masyn winn": {
      "SLG": 0.25,
      "xSLG": 0.316,
      "Barrel%": 2.9,
      "HardHit%": 26.5,
      "EV50": 92.59259697,
      "BABIP": 0.235,
      "xwOBA": null,
      "wOBA": 0.297
    },
    "fernando tatis jr": {
      "SLG": 0.303,
      "xSLG": 0.418,
      "Barrel%": 13.7,
      "HardHit%": 72.5,
      "EV50": 99.7033728,
      "BABIP": 0.32,
      "xwOBA": null,
      "wOBA": 0.287
    },
    "blake perkins": {
      "SLG": 0.207,
      "xSLG": 0.225,
      "Barrel%": 4.8,
      "HardHit%": 23.8,
      "EV50": 91.9712145,
      "BABIP": 0.2,
      "xwOBA": null,
      "wOBA": 0.22
    },
    "sam haggerty": {
      "SLG": 0.2,
      "xSLG": 0.225,
      "Barrel%": 0.0,
      "HardHit%": 0.0,
      "EV50": 89.924024,
      "BABIP": 0.4,
      "xwOBA": null,
      "wOBA": 0.23
    },
    "josh smith": {
      "SLG": 0.18,
      "xSLG": 0.336,
      "Barrel%": 4.9,
      "HardHit%": 34.1,
      "EV50": 93.10979125,
      "BABIP": 0.22,
      "xwOBA": null,
      "wOBA": 0.214
    },
    "jonathan india": {
      "SLG": 0.325,
      "xSLG": 0.3,
      "Barrel%": 6.9,
      "HardHit%": 31.0,
      "EV50": 92.602764483,
      "BABIP": 0.185,
      "xwOBA": null,
      "wOBA": 0.319
    },
    "jake mccarthy": {
      "SLG": 0.313,
      "xSLG": 0.392,
      "Barrel%": 7.4,
      "HardHit%": 29.6,
      "EV50": 93.353312174,
      "BABIP": 0.25,
      "xwOBA": null,
      "wOBA": 0.273
    },
    "kyle isbel": {
      "SLG": 0.487,
      "xSLG": 0.358,
      "Barrel%": 6.7,
      "HardHit%": 40.0,
      "EV50": 94.464752963,
      "BABIP": 0.385,
      "xwOBA": null,
      "wOBA": 0.393
    },
    "christian yelich": {
      "SLG": 0.451,
      "xSLG": 0.369,
      "Barrel%": 5.4,
      "HardHit%": 40.5,
      "EV50": 94.788898889,
      "BABIP": 0.417,
      "xwOBA": null,
      "wOBA": 0.359
    },
    "alek thomas": {
      "SLG": 0.204,
      "xSLG": 0.351,
      "Barrel%": 5.7,
      "HardHit%": 45.7,
      "EV50": 95.52304125,
      "BABIP": 0.176,
      "xwOBA": null,
      "wOBA": 0.176
    },
    "leody taveras": {
      "SLG": 0.464,
      "xSLG": 0.417,
      "Barrel%": 4.8,
      "HardHit%": 38.1,
      "EV50": 93.481113,
      "BABIP": 0.5,
      "xwOBA": null,
      "wOBA": 0.427
    },
    "jonny deluca": {
      "SLG": 0.412,
      "xSLG": 0.407,
      "Barrel%": 3.6,
      "HardHit%": 28.6,
      "EV50": 93.629342308,
      "BABIP": 0.296,
      "xwOBA": null,
      "wOBA": 0.311
    },
    "luken baker": {
      "SLG": 0.2,
      "xSLG": 0.15,
      "Barrel%": 0.0,
      "HardHit%": 50.0,
      "EV50": 97.390135,
      "BABIP": 0.5,
      "xwOBA": null,
      "wOBA": 0.182
    },
    "ben williamson": {
      "SLG": 0.354,
      "xSLG": 0.318,
      "Barrel%": 0.0,
      "HardHit%": 34.2,
      "EV50": 92.91488973,
      "BABIP": 0.351,
      "xwOBA": null,
      "wOBA": 0.319
    },
    "daulton varsho": {
      "SLG": 0.491,
      "xSLG": 0.422,
      "Barrel%": 6.1,
      "HardHit%": 34.7,
      "EV50": 92.694672245,
      "BABIP": 0.261,
      "xwOBA": null,
      "wOBA": 0.36
    },
    "jc escarra": {
      "SLG": 0.0,
      "xSLG": 0.139,
      "Barrel%": 0.0,
      "HardHit%": 25.0,
      "EV50": 94.10774125,
      "BABIP": 0.0,
      "xwOBA": null,
      "wOBA": 0.059
    },
    "jose trevino": {
      "SLG": 0.091,
      "xSLG": 0.223,
      "Barrel%": 0.0,
      "HardHit%": 25.0,
      "EV50": 90.792392857,
      "BABIP": 0.125,
      "xwOBA": null,
      "wOBA": 0.135
    },
    "chase meidroth": {
      "SLG": 0.305,
      "xSLG": 0.329,
      "Barrel%": 4.4,
      "HardHit%": 42.2,
      "EV50": 93.357817209,
      "BABIP": 0.256,
      "xwOBA": null,
      "wOBA": 0.283
    },
    "reese mcguire": {
      "SLG": 0.125,
      "xSLG": 0.137,
      "Barrel%": 0.0,
      "HardHit%": 10.0,
      "EV50": 89.111222,
      "BABIP": 0.2,
      "xwOBA": null,
      "wOBA": 0.151
    },
    "shea langeliers": {
      "SLG": 0.563,
      "xSLG": 0.493,
      "Barrel%": 12.2,
      "HardHit%": 43.9,
      "EV50": 95.466860244,
      "BABIP": 0.389,
      "xwOBA": null,
      "wOBA": 0.4
    },
    "gabriel arias": {
      "SLG": 0.433,
      "xSLG": 0.414,
      "Barrel%": 16.7,
      "HardHit%": 50.0,
      "EV50": 97.075641765,
      "BABIP": 0.25,
      "xwOBA": null,
      "wOBA": 0.302
    },
    "lenyn sosa": {
      "SLG": 0.324,
      "xSLG": 0.361,
      "Barrel%": 0.0,
      "HardHit%": 40.7,
      "EV50": 93.594833704,
      "BABIP": 0.296,
      "xwOBA": null,
      "wOBA": 0.248
    },
    "ryan ohearn": {
      "SLG": 0.508,
      "xSLG": 0.531,
      "Barrel%": 10.0,
      "HardHit%": 44.0,
      "EV50": 94.543284,
      "BABIP": 0.319,
      "xwOBA": null,
      "wOBA": 0.393
    },
    "nolan gorman": {
      "SLG": 0.327,
      "xSLG": 0.337,
      "Barrel%": 6.3,
      "HardHit%": 40.6,
      "EV50": 93.909036875,
      "BABIP": 0.267,
      "xwOBA": null,
      "wOBA": 0.277
    },
    "julio rodriguez": {
      "SLG": 0.279,
      "xSLG": 0.296,
      "Barrel%": 4.2,
      "HardHit%": 37.5,
      "EV50": 94.563335833,
      "BABIP": 0.277,
      "xwOBA": null,
      "wOBA": 0.275
    },
    "taylor walls": {
      "SLG": 0.381,
      "xSLG": 0.261,
      "Barrel%": 0.0,
      "HardHit%": 15.8,
      "EV50": 90.773208,
      "BABIP": 0.438,
      "xwOBA": null,
      "wOBA": 0.357
    },
    "ernie clement": {
      "SLG": 0.379,
      "xSLG": 0.378,
      "Barrel%": 0.0,
      "HardHit%": 27.0,
      "EV50": 92.08762371,
      "BABIP": 0.317,
      "xwOBA": null,
      "wOBA": 0.311
    },
    "james outman": {
      "SLG": 0.0,
      "xSLG": 0.066,
      "Barrel%": 0.0,
      "HardHit%": 25.0,
      "EV50": 90.87049375,
      "BABIP": 0.0,
      "xwOBA": null,
      "wOBA": 0.037
    },
    "henry davis": {
      "SLG": 0.314,
      "xSLG": 0.26,
      "Barrel%": 7.7,
      "HardHit%": 34.6,
      "EV50": 94.274539615,
      "BABIP": 0.308,
      "xwOBA": null,
      "wOBA": 0.301
    },
    "heriberto hernandez": {
      "SLG": 0.209,
      "xSLG": 0.309,
      "Barrel%": 6.1,
      "HardHit%": 42.4,
      "EV50": 94.783472424,
      "BABIP": 0.212,
      "xwOBA": null,
      "wOBA": 0.242
    },
    "jordan walker": {
      "SLG": 0.734,
      "xSLG": 0.758,
      "Barrel%": 24.4,
      "HardHit%": 62.2,
      "EV50": 98.805190889,
      "BABIP": 0.351,
      "xwOBA": null,
      "wOBA": 0.482
    },
    "tanner murray": {
      "SLG": 0.4,
      "xSLG": 0.366,
      "Barrel%": 7.7,
      "HardHit%": 46.2,
      "EV50": 94.106510833,
      "BABIP": 0.167,
      "xwOBA": null,
      "wOBA": 0.262
    },
    "jeferson quero": {
      "SLG": 0.0,
      "xSLG": 0.355,
      "Barrel%": 0.0,
      "HardHit%": 0.0,
      "EV50": 88.0,
      "BABIP": 0.0,
      "xwOBA": null,
      "wOBA": 0.356
    },
    "nathan lukes": {
      "SLG": 0.071,
      "xSLG": 0.252,
      "Barrel%": 0.0,
      "HardHit%": 26.1,
      "EV50": 91.676205217,
      "BABIP": 0.087,
      "xwOBA": null,
      "wOBA": 0.106
    },
    "colt keith": {
      "SLG": 0.463,
      "xSLG": 0.495,
      "Barrel%": 9.8,
      "HardHit%": 56.1,
      "EV50": 96.518303171,
      "BABIP": 0.439,
      "xwOBA": null,
      "wOBA": 0.372
    },
    "cam smith": {
      "SLG": 0.484,
      "xSLG": 0.528,
      "Barrel%": 17.0,
      "HardHit%": 53.2,
      "EV50": 96.943525,
      "BABIP": 0.341,
      "xwOBA": null,
      "wOBA": 0.378
    },
    "gabriel moreno": {
      "SLG": 0.4,
      "xSLG": 0.426,
      "Barrel%": 9.1,
      "HardHit%": 42.4,
      "EV50": 93.803654242,
      "BABIP": 0.333,
      "xwOBA": null,
      "wOBA": 0.329
    },
    "richie palacios": {
      "SLG": 0.368,
      "xSLG": 0.501,
      "Barrel%": 12.5,
      "HardHit%": 50.0,
      "EV50": 94.878576875,
      "BABIP": 0.2,
      "xwOBA": null,
      "wOBA": 0.367
    },
    "jeremy pena": {
      "SLG": 0.349,
      "xSLG": 0.449,
      "Barrel%": 2.7,
      "HardHit%": 29.7,
      "EV50": 92.871165405,
      "BABIP": 0.297,
      "xwOBA": null,
      "wOBA": 0.297
    },
    "joey bart": {
      "SLG": 0.273,
      "xSLG": 0.114,
      "Barrel%": 0.0,
      "HardHit%": 25.0,
      "EV50": 91.819308333,
      "BABIP": 0.182,
      "xwOBA": null,
      "wOBA": 0.234
    },
    "darell hernaiz": {
      "SLG": 0.188,
      "xSLG": 0.231,
      "Barrel%": 0.0,
      "HardHit%": 27.3,
      "EV50": 92.513344545,
      "BABIP": 0.273,
      "xwOBA": null,
      "wOBA": 0.202
    },
    "zach neto": {
      "SLG": 0.479,
      "xSLG": 0.421,
      "Barrel%": 12.5,
      "HardHit%": 37.5,
      "EV50": 94.144070426,
      "BABIP": 0.279,
      "xwOBA": null,
      "wOBA": 0.367
    },
    "michael busch": {
      "SLG": 0.196,
      "xSLG": 0.263,
      "Barrel%": 4.5,
      "HardHit%": 31.8,
      "EV50": 92.200410682,
      "BABIP": 0.205,
      "xwOBA": null,
      "wOBA": 0.233
    },
    "jake fraley": {
      "SLG": 0.313,
      "xSLG": 0.3,
      "Barrel%": 4.0,
      "HardHit%": 24.0,
      "EV50": 92.1970352,
      "BABIP": 0.28,
      "xwOBA": null,
      "wOBA": 0.288
    },
    "rece hinds": {
      "SLG": 0.0,
      "xSLG": 0.06,
      "Barrel%": 0.0,
      "HardHit%": 0.0,
      "EV50": 88.0,
      "BABIP": 0.0,
      "xwOBA": null,
      "wOBA": 0.0
    },
    "kyle schwarber": {
      "SLG": 0.593,
      "xSLG": 0.559,
      "Barrel%": 27.3,
      "HardHit%": 51.5,
      "EV50": 96.130201515,
      "BABIP": 0.296,
      "xwOBA": null,
      "wOBA": 0.434
    },
    "caleb durbin": {
      "SLG": 0.164,
      "xSLG": 0.244,
      "Barrel%": 0.0,
      "HardHit%": 23.9,
      "EV50": 91.740078864,
      "BABIP": 0.152,
      "xwOBA": null,
      "wOBA": 0.196
    },
    "jackson merrill": {
      "SLG": 0.453,
      "xSLG": 0.518,
      "Barrel%": 13.0,
      "HardHit%": 50.0,
      "EV50": 94.902115849,
      "BABIP": 0.26,
      "xwOBA": null,
      "wOBA": 0.337
    },
    "luis robert jr": {
      "SLG": 0.37,
      "xSLG": 0.415,
      "Barrel%": 5.0,
      "HardHit%": 42.5,
      "EV50": 95.545569,
      "BABIP": 0.316,
      "xwOBA": null,
      "wOBA": 0.359
    },
    "kyle tucker": {
      "SLG": 0.306,
      "xSLG": 0.298,
      "Barrel%": 2.2,
      "HardHit%": 39.1,
      "EV50": 93.217785435,
      "BABIP": 0.311,
      "xwOBA": null,
      "wOBA": 0.317
    },
    "riley greene": {
      "SLG": 0.349,
      "xSLG": 0.519,
      "Barrel%": 12.8,
      "HardHit%": 51.1,
      "EV50": 95.842274468,
      "BABIP": 0.304,
      "xwOBA": null,
      "wOBA": 0.316
    },
    "ezequiel duran": {
      "SLG": 0.364,
      "xSLG": 0.351,
      "Barrel%": 4.3,
      "HardHit%": 47.8,
      "EV50": 94.972763636,
      "BABIP": 0.318,
      "xwOBA": null,
      "wOBA": 0.305
    },
    "carter jensen": {
      "SLG": 0.511,
      "xSLG": 0.461,
      "Barrel%": 16.7,
      "HardHit%": 46.7,
      "EV50": 96.629151667,
      "BABIP": 0.231,
      "xwOBA": null,
      "wOBA": 0.335
    },
    "andrew benintendi": {
      "SLG": 0.25,
      "xSLG": 0.303,
      "Barrel%": 10.0,
      "HardHit%": 60.0,
      "EV50": 94.587502105,
      "BABIP": 0.35,
      "xwOBA": null,
      "wOBA": 0.235
    },
    "konnor griffin": {
      "SLG": 0.243,
      "xSLG": 0.26,
      "Barrel%": 7.7,
      "HardHit%": 26.9,
      "EV50": 93.892891538,
      "BABIP": 0.269,
      "xwOBA": null,
      "wOBA": 0.25
    },
    "dustin harris": {
      "SLG": 0.333,
      "xSLG": 0.368,
      "Barrel%": 0.0,
      "HardHit%": 18.2,
      "EV50": 91.399514545,
      "BABIP": 0.273,
      "xwOBA": null,
      "wOBA": 0.372
    },
    "curtis mead": {
      "SLG": 0.414,
      "xSLG": 0.457,
      "Barrel%": 8.0,
      "HardHit%": 44.0,
      "EV50": 94.8788732,
      "BABIP": 0.25,
      "xwOBA": null,
      "wOBA": 0.339
    },
    "edouard julien": {
      "SLG": 0.429,
      "xSLG": 0.467,
      "Barrel%": 11.5,
      "HardHit%": 46.2,
      "EV50": 94.966686923,
      "BABIP": 0.4,
      "xwOBA": null,
      "wOBA": 0.37
    },
    "brendan donovan": {
      "SLG": 0.542,
      "xSLG": 0.349,
      "Barrel%": 5.1,
      "HardHit%": 28.2,
      "EV50": 91.969024615,
      "BABIP": 0.306,
      "xwOBA": null,
      "wOBA": 0.424
    },
    "connor joe": {
      "SLG": 0.0,
      "xSLG": 0.212,
      "Barrel%": 0.0,
      "HardHit%": 50.0,
      "EV50": 99.35298,
      "BABIP": 0.0,
      "xwOBA": null,
      "wOBA": 0.0
    },
    "aaron judge": {
      "SLG": 0.547,
      "xSLG": 0.653,
      "Barrel%": 28.6,
      "HardHit%": 52.4,
      "EV50": 97.308908571,
      "BABIP": 0.25,
      "xwOBA": null,
      "wOBA": 0.384
    },
    "brooks lee": {
      "SLG": 0.44,
      "xSLG": 0.312,
      "Barrel%": 5.1,
      "HardHit%": 38.5,
      "EV50": 93.074938378,
      "BABIP": 0.25,
      "xwOBA": null,
      "wOBA": 0.322
    },
    "jung hoo lee": {
      "SLG": 0.345,
      "xSLG": 0.329,
      "Barrel%": 2.0,
      "HardHit%": 38.0,
      "EV50": 92.9744544,
      "BABIP": 0.224,
      "xwOBA": null,
      "wOBA": 0.271
    },
    "nathaniel lowe": {
      "SLG": 0.316,
      "xSLG": 0.329,
      "Barrel%": 0.0,
      "HardHit%": 53.3,
      "EV50": 95.657349333,
      "BABIP": 0.267,
      "xwOBA": null,
      "wOBA": 0.315
    },
    "gunnar henderson": {
      "SLG": 0.542,
      "xSLG": 0.426,
      "Barrel%": 12.2,
      "HardHit%": 46.9,
      "EV50": 94.888618571,
      "BABIP": 0.233,
      "xwOBA": null,
      "wOBA": 0.371
    },
    "yandy diaz": {
      "SLG": 0.556,
      "xSLG": 0.451,
      "Barrel%": 7.3,
      "HardHit%": 49.1,
      "EV50": 96.237551455,
      "BABIP": 0.385,
      "xwOBA": null,
      "wOBA": 0.447
    },
    "cj kayfus": {
      "SLG": 0.364,
      "xSLG": 0.427,
      "Barrel%": 21.4,
      "HardHit%": 50.0,
      "EV50": 94.712108571,
      "BABIP": 0.231,
      "xwOBA": null,
      "wOBA": 0.296
    },
    "willi castro": {
      "SLG": 0.309,
      "xSLG": 0.285,
      "Barrel%": 6.5,
      "HardHit%": 35.5,
      "EV50": 93.611364839,
      "BABIP": 0.333,
      "xwOBA": null,
      "wOBA": 0.258
    },
    "christian walker": {
      "SLG": 0.594,
      "xSLG": 0.512,
      "Barrel%": 15.1,
      "HardHit%": 49.1,
      "EV50": 95.533666981,
      "BABIP": 0.327,
      "xwOBA": null,
      "wOBA": 0.427
    },
    "geraldo perdomo": {
      "SLG": 0.276,
      "xSLG": 0.281,
      "Barrel%": 1.8,
      "HardHit%": 29.1,
      "EV50": 92.816372308,
      "BABIP": 0.189,
      "xwOBA": null,
      "wOBA": 0.279
    },
    "james mccann": {
      "SLG": 0.375,
      "xSLG": 0.345,
      "Barrel%": 12.5,
      "HardHit%": 43.8,
      "EV50": 96.427002,
      "BABIP": 0.4,
      "xwOBA": null,
      "wOBA": 0.293
    },
    "jose tena": {
      "SLG": 0.308,
      "xSLG": 0.27,
      "Barrel%": 0.0,
      "HardHit%": 20.0,
      "EV50": 91.3898255,
      "BABIP": 0.4,
      "xwOBA": null,
      "wOBA": 0.312
    },
    "seiya suzuki": {
      "SLG": 0.211,
      "xSLG": 0.218,
      "Barrel%": 0.0,
      "HardHit%": 38.5,
      "EV50": 93.547369231,
      "BABIP": 0.308,
      "xwOBA": null,
      "wOBA": 0.282
    },
    "carlos cortes": {
      "SLG": 0.5,
      "xSLG": 0.517,
      "Barrel%": 13.0,
      "HardHit%": 43.5,
      "EV50": 93.916707727,
      "BABIP": 0.273,
      "xwOBA": null,
      "wOBA": 0.399
    },
    "lawrence butler": {
      "SLG": 0.314,
      "xSLG": 0.386,
      "Barrel%": 5.6,
      "HardHit%": 47.2,
      "EV50": 95.577000556,
      "BABIP": 0.206,
      "xwOBA": null,
      "wOBA": 0.259
    },
    "wenceel perez": {
      "SLG": 0.0,
      "xSLG": 0.499,
      "Barrel%": 10.0,
      "HardHit%": 50.0,
      "EV50": 95.106741,
      "BABIP": 0.0,
      "xwOBA": null,
      "wOBA": 0.065
    },
    "kebryan hayes": {
      "SLG": 0.073,
      "xSLG": 0.397,
      "Barrel%": 5.3,
      "HardHit%": 36.8,
      "EV50": 93.659996857,
      "BABIP": 0.079,
      "xwOBA": null,
      "wOBA": 0.111
    },
    "connor wong": {
      "SLG": 0.563,
      "xSLG": 0.356,
      "Barrel%": 0.0,
      "HardHit%": 58.3,
      "EV50": 96.0138025,
      "BABIP": 0.5,
      "xwOBA": null,
      "wOBA": 0.433
    },
    "royce lewis": {
      "SLG": 0.444,
      "xSLG": 0.382,
      "Barrel%": 12.5,
      "HardHit%": 54.2,
      "EV50": 96.257290417,
      "BABIP": 0.273,
      "xwOBA": null,
      "wOBA": 0.375
    },
    "jorge soler": {
      "SLG": 0.508,
      "xSLG": 0.438,
      "Barrel%": 14.6,
      "HardHit%": 41.5,
      "EV50": 94.357611707,
      "BABIP": 0.278,
      "xwOBA": null,
      "wOBA": 0.372
    },
    "junior caminero": {
      "SLG": 0.367,
      "xSLG": 0.393,
      "Barrel%": 8.5,
      "HardHit%": 36.2,
      "EV50": 94.870918723,
      "BABIP": 0.267,
      "xwOBA": null,
      "wOBA": 0.33
    },
    "adolis garcia": {
      "SLG": 0.361,
      "xSLG": 0.388,
      "Barrel%": 11.6,
      "HardHit%": 48.8,
      "EV50": 95.480747674,
      "BABIP": 0.268,
      "xwOBA": null,
      "wOBA": 0.296
    },
    "dylan moore": {
      "SLG": 0.0,
      "xSLG": 0.095,
      "Barrel%": 0.0,
      "HardHit%": 0.0,
      "EV50": 90.87126,
      "BABIP": 0.0,
      "xwOBA": null,
      "wOBA": 0.178
    },
    "zack gelof": {
      "SLG": 0.0,
      "xSLG": 0.0,
      "Barrel%": 0.0,
      "HardHit%": 0.0,
      "EV50": null,
      "BABIP": 0.0,
      "xwOBA": null,
      "wOBA": 0.0
    },
    "shay whitcomb": {
      "SLG": 0.0,
      "xSLG": 0.0,
      "Barrel%": null,
      "HardHit%": null,
      "EV50": null,
      "BABIP": 0.0,
      "xwOBA": null,
      "wOBA": 0.237
    },
    "jared young": {
      "SLG": 0.45,
      "xSLG": 0.39,
      "Barrel%": 16.7,
      "HardHit%": 50.0,
      "EV50": 96.474591765,
      "BABIP": 0.389,
      "xwOBA": null,
      "wOBA": 0.372
    },
    "george valera": {
      "SLG": 0.5,
      "xSLG": 0.329,
      "Barrel%": 0.0,
      "HardHit%": 75.0,
      "EV50": 98.4373425,
      "BABIP": 0.25,
      "xwOBA": null,
      "wOBA": 0.323
    },
    "jorge polanco": {
      "SLG": 0.286,
      "xSLG": 0.32,
      "Barrel%": 4.4,
      "HardHit%": 33.3,
      "EV50": 93.223895778,
      "BABIP": 0.205,
      "xwOBA": null,
      "wOBA": 0.246
    },
    "nico hoerner": {
      "SLG": 0.455,
      "xSLG": 0.373,
      "Barrel%": 0.0,
      "HardHit%": 24.1,
      "EV50": 91.596837544,
      "BABIP": 0.333,
      "xwOBA": null,
      "wOBA": 0.384
    },
    "pavin smith": {
      "SLG": 0.167,
      "xSLG": 0.162,
      "Barrel%": 0.0,
      "HardHit%": 50.0,
      "EV50": 94.5265775,
      "BABIP": 0.25,
      "xwOBA": null,
      "wOBA": 0.292
    },
    "chandler simpson": {
      "SLG": 0.475,
      "xSLG": 0.354,
      "Barrel%": 0.0,
      "HardHit%": 13.8,
      "EV50": 90.604406296,
      "BABIP": 0.429,
      "xwOBA": null,
      "wOBA": 0.41
    },
    "william contreras": {
      "SLG": 0.473,
      "xSLG": 0.419,
      "Barrel%": 4.3,
      "HardHit%": 45.7,
      "EV50": 94.949420435,
      "BABIP": 0.318,
      "xwOBA": null,
      "wOBA": 0.389
    },
    "travis darnaud": {
      "SLG": 0.2,
      "xSLG": 0.446,
      "Barrel%": 33.3,
      "HardHit%": 33.3,
      "EV50": 92.322176667,
      "BABIP": 0.167,
      "xwOBA": null,
      "wOBA": 0.129
    },
    "christian vazquez": {
      "SLG": 0.63,
      "xSLG": 0.33,
      "Barrel%": 4.5,
      "HardHit%": 27.3,
      "EV50": 92.246826667,
      "BABIP": 0.45,
      "xwOBA": null,
      "wOBA": 0.448
    },
    "myles straw": {
      "SLG": 0.438,
      "xSLG": 0.504,
      "Barrel%": 0.0,
      "HardHit%": 26.7,
      "EV50": 92.516072143,
      "BABIP": 0.4,
      "xwOBA": null,
      "wOBA": 0.386
    },
    "kevin mcgonigle": {
      "SLG": 0.492,
      "xSLG": 0.546,
      "Barrel%": 9.4,
      "HardHit%": 37.7,
      "EV50": 93.743693208,
      "BABIP": 0.346,
      "xwOBA": null,
      "wOBA": 0.408
    },
    "miguel amaya": {
      "SLG": 0.44,
      "xSLG": 0.33,
      "Barrel%": 6.3,
      "HardHit%": 25.0,
      "EV50": 91.784151875,
      "BABIP": 0.4,
      "xwOBA": null,
      "wOBA": 0.405
    },
    "yordan alvarez": {
      "SLG": 0.7,
      "xSLG": 0.799,
      "Barrel%": 19.2,
      "HardHit%": 46.2,
      "EV50": 96.416902308,
      "BABIP": 0.283,
      "xwOBA": null,
      "wOBA": 0.489
    },
    "jared oliva": {
      "SLG": 0.143,
      "xSLG": 0.379,
      "Barrel%": 0.0,
      "HardHit%": 66.7,
      "EV50": 96.704105,
      "BABIP": 0.167,
      "xwOBA": null,
      "wOBA": 0.13
    },
    "eli white": {
      "SLG": 0.231,
      "xSLG": 0.238,
      "Barrel%": 0.0,
      "HardHit%": 16.7,
      "EV50": 89.722045833,
      "BABIP": 0.167,
      "xwOBA": null,
      "wOBA": 0.194
    },
    "freddie freeman": {
      "SLG": 0.457,
      "xSLG": 0.618,
      "Barrel%": 16.7,
      "HardHit%": 51.7,
      "EV50": 95.800835,
      "BABIP": 0.263,
      "xwOBA": null,
      "wOBA": 0.34
    },
    "logan ohoppe": {
      "SLG": 0.235,
      "xSLG": 0.272,
      "Barrel%": 7.3,
      "HardHit%": 39.0,
      "EV50": 93.912655122,
      "BABIP": 0.268,
      "xwOBA": null,
      "wOBA": 0.283
    },
    "shohei ohtani": {
      "SLG": 0.508,
      "xSLG": 0.545,
      "Barrel%": 23.9,
      "HardHit%": 52.2,
      "EV50": 96.870337609,
      "BABIP": 0.268,
      "xwOBA": null,
      "wOBA": 0.388
    },
    "randy arozarena": {
      "SLG": 0.381,
      "xSLG": 0.431,
      "Barrel%": 8.0,
      "HardHit%": 42.0,
      "EV50": 94.8009766,
      "BABIP": 0.347,
      "xwOBA": null,
      "wOBA": 0.369
    },
    "christian koss": {
      "SLG": 0.286,
      "xSLG": 0.18,
      "Barrel%": 0.0,
      "HardHit%": 28.6,
      "EV50": 92.047847143,
      "BABIP": 0.143,
      "xwOBA": null,
      "wOBA": 0.185
    },
    "braxton fulford": {
      "SLG": 1.0,
      "xSLG": 0.17,
      "Barrel%": 0.0,
      "HardHit%": 66.7,
      "EV50": 93.584133333,
      "BABIP": 0.5,
      "xwOBA": null,
      "wOBA": 0.604
    },
    "brent rooker": {
      "SLG": 0.293,
      "xSLG": 0.371,
      "Barrel%": 19.2,
      "HardHit%": 42.3,
      "EV50": 94.540330769,
      "BABIP": 0.167,
      "xwOBA": null,
      "wOBA": 0.248
    },
    "isaac collins": {
      "SLG": 0.31,
      "xSLG": 0.267,
      "Barrel%": 11.1,
      "HardHit%": 33.3,
      "EV50": 93.998251111,
      "BABIP": 0.308,
      "xwOBA": null,
      "wOBA": 0.302
    },
    "kody clemens": {
      "SLG": 0.355,
      "xSLG": 0.436,
      "Barrel%": 22.2,
      "HardHit%": 33.3,
      "EV50": 94.403307222,
      "BABIP": 0.188,
      "xwOBA": null,
      "wOBA": 0.304
    },
    "teoscar hernandez": {
      "SLG": 0.519,
      "xSLG": 0.432,
      "Barrel%": 11.1,
      "HardHit%": 38.9,
      "EV50": 93.935068333,
      "BABIP": 0.394,
      "xwOBA": null,
      "wOBA": 0.376
    },
    "bo bichette": {
      "SLG": 0.307,
      "xSLG": 0.373,
      "Barrel%": 1.8,
      "HardHit%": 39.3,
      "EV50": 94.55010625,
      "BABIP": 0.291,
      "xwOBA": null,
      "wOBA": 0.264
    },
    "xander bogaerts": {
      "SLG": 0.397,
      "xSLG": 0.484,
      "Barrel%": 7.0,
      "HardHit%": 40.4,
      "EV50": 94.785804912,
      "BABIP": 0.273,
      "xwOBA": null,
      "wOBA": 0.332
    },
    "moises ballesteros": {
      "SLG": 0.526,
      "xSLG": 0.528,
      "Barrel%": 16.7,
      "HardHit%": 60.0,
      "EV50": 96.64695,
      "BABIP": 0.393,
      "xwOBA": null,
      "wOBA": 0.399
    },
    "drake baldwin": {
      "SLG": 0.554,
      "xSLG": 0.583,
      "Barrel%": 16.4,
      "HardHit%": 42.6,
      "EV50": 95.055750492,
      "BABIP": 0.321,
      "xwOBA": null,
      "wOBA": 0.413
    },
    "parker meadows": {
      "SLG": 0.333,
      "xSLG": 0.277,
      "Barrel%": 3.8,
      "HardHit%": 19.2,
      "EV50": 91.241073077,
      "BABIP": 0.346,
      "xwOBA": null,
      "wOBA": 0.294
    },
    "masataka yoshida": {
      "SLG": 0.391,
      "xSLG": 0.329,
      "Barrel%": 0.0,
      "HardHit%": 63.2,
      "EV50": 97.021965789,
      "BABIP": 0.368,
      "xwOBA": null,
      "wOBA": 0.424
    },
    "sal frelick": {
      "SLG": 0.288,
      "xSLG": 0.307,
      "Barrel%": 2.4,
      "HardHit%": 26.8,
      "EV50": 92.9506075,
      "BABIP": 0.225,
      "xwOBA": null,
      "wOBA": 0.294
    },
    "oneil cruz": {
      "SLG": 0.597,
      "xSLG": 0.588,
      "Barrel%": 20.5,
      "HardHit%": 61.4,
      "EV50": 100.108495455,
      "BABIP": 0.436,
      "xwOBA": null,
      "wOBA": 0.435
    },
    "tyler freeman": {
      "SLG": 0.261,
      "xSLG": 0.415,
      "Barrel%": 0.0,
      "HardHit%": 35.0,
      "EV50": 92.89883,
      "BABIP": 0.316,
      "xwOBA": null,
      "wOBA": 0.311
    },
    "mitch garver": {
      "SLG": 0.167,
      "xSLG": 0.251,
      "Barrel%": 0.0,
      "HardHit%": 57.1,
      "EV50": 96.090895714,
      "BABIP": 0.286,
      "xwOBA": null,
      "wOBA": 0.264
    },
    "cody bellinger": {
      "SLG": 0.339,
      "xSLG": 0.404,
      "Barrel%": 7.8,
      "HardHit%": 39.2,
      "EV50": 93.1304108,
      "BABIP": 0.26,
      "xwOBA": null,
      "wOBA": 0.306
    },
    "trevor story": {
      "SLG": 0.274,
      "xSLG": 0.309,
      "Barrel%": 3.9,
      "HardHit%": 39.2,
      "EV50": 93.375999412,
      "BABIP": 0.26,
      "xwOBA": null,
      "wOBA": 0.208
    },
    "victor caratini": {
      "SLG": 0.333,
      "xSLG": 0.47,
      "Barrel%": 6.7,
      "HardHit%": 40.0,
      "EV50": 93.776642444,
      "BABIP": 0.273,
      "xwOBA": null,
      "wOBA": 0.327
    },
    "andrew mccutchen": {
      "SLG": 0.423,
      "xSLG": 0.416,
      "Barrel%": 20.0,
      "HardHit%": 46.7,
      "EV50": 95.077933333,
      "BABIP": 0.357,
      "xwOBA": null,
      "wOBA": 0.301
    },
    "ryan vilade": {
      "SLG": 0.316,
      "xSLG": 0.327,
      "Barrel%": 0.0,
      "HardHit%": 23.1,
      "EV50": 92.604223077,
      "BABIP": 0.385,
      "xwOBA": null,
      "wOBA": 0.282
    },
    "austin wells": {
      "SLG": 0.267,
      "xSLG": 0.396,
      "Barrel%": 9.1,
      "HardHit%": 54.5,
      "EV50": 96.455396061,
      "BABIP": 0.219,
      "xwOBA": null,
      "wOBA": 0.257
    },
    "owen caissie": {
      "SLG": 0.449,
      "xSLG": 0.467,
      "Barrel%": 22.2,
      "HardHit%": 48.1,
      "EV50": 96.445437778,
      "BABIP": 0.4,
      "xwOBA": null,
      "wOBA": 0.335
    },
    "brandon lowe": {
      "SLG": 0.679,
      "xSLG": 0.461,
      "Barrel%": 11.9,
      "HardHit%": 42.9,
      "EV50": 93.698068571,
      "BABIP": 0.229,
      "xwOBA": null,
      "wOBA": 0.462
    },
    "matt mclain": {
      "SLG": 0.258,
      "xSLG": 0.359,
      "Barrel%": 8.7,
      "HardHit%": 28.3,
      "EV50": 93.046344889,
      "BABIP": 0.283,
      "xwOBA": null,
      "wOBA": 0.292
    },
    "dansby swanson": {
      "SLG": 0.345,
      "xSLG": 0.38,
      "Barrel%": 13.5,
      "HardHit%": 56.8,
      "EV50": 95.509360811,
      "BABIP": 0.176,
      "xwOBA": null,
      "wOBA": 0.316
    },
    "kazuma okamoto": {
      "SLG": 0.345,
      "xSLG": 0.364,
      "Barrel%": 8.3,
      "HardHit%": 38.9,
      "EV50": 94.2181175,
      "BABIP": 0.324,
      "xwOBA": null,
      "wOBA": 0.295
    },
    "michael conforto": {
      "SLG": 0.364,
      "xSLG": 0.434,
      "Barrel%": 8.3,
      "HardHit%": 50.0,
      "EV50": 96.133666667,
      "BABIP": 0.5,
      "xwOBA": null,
      "wOBA": 0.375
    },
    "ketel marte": {
      "SLG": 0.424,
      "xSLG": 0.522,
      "Barrel%": 9.6,
      "HardHit%": 48.1,
      "EV50": 96.277365192,
      "BABIP": 0.208,
      "xwOBA": null,
      "wOBA": 0.314
    },
    "deyvison de los santos": {
      "SLG": 0.5,
      "xSLG": 0.509,
      "Barrel%": 50.0,
      "HardHit%": 50.0,
      "EV50": 99.59281,
      "BABIP": 0.5,
      "xwOBA": null,
      "wOBA": 0.323
    },
    "patrick bailey": {
      "SLG": 0.136,
      "xSLG": 0.373,
      "Barrel%": 5.3,
      "HardHit%": 36.8,
      "EV50": 93.107228378,
      "BABIP": 0.158,
      "xwOBA": null,
      "wOBA": 0.162
    },
    "josh lowe": {
      "SLG": 0.293,
      "xSLG": 0.256,
      "Barrel%": 11.1,
      "HardHit%": 22.2,
      "EV50": 91.562827308,
      "BABIP": 0.125,
      "xwOBA": null,
      "wOBA": 0.242
    },
    "ryan kreidler": {
      "SLG": 0.5,
      "xSLG": 0.698,
      "Barrel%": 14.3,
      "HardHit%": 14.3,
      "EV50": 91.962428571,
      "BABIP": 0.0,
      "xwOBA": null,
      "wOBA": 0.264
    },
    "brandon valenzuela": {
      "SLG": 0.3,
      "xSLG": 0.322,
      "Barrel%": 9.1,
      "HardHit%": 36.4,
      "EV50": 93.335279091,
      "BABIP": 0.2,
      "xwOBA": null,
      "wOBA": 0.221
    }
  },
  "league_avg": {
    "SLG": 0.354,
    "xSLG": 0.375,
    "Barrel%": 7.761,
    "HardHit%": 38.971,
    "EV50": 94.115,
    "BABIP": 0.28,
    "wOBA": 0.303
  },
  "cols": [
    "SLG",
    "xSLG",
    "Barrel%",
    "HardHit%",
    "EV50",
    "BABIP",
    "xwOBA",
    "wOBA"
  ]
}